DigitalCircuitsExperiments/DCE02/encode_32to5_for/encode_32to5_for.v
module encode_32to5_for(x, en, y);
    input [31:0] x;
    input en;
    output reg [4:0] y;
    integer i;
    always @ (x or en)
        begin
            if (en)
                begin
                    y = 0;
                    for (i = 0; i<= 31; i = i + 1)
                        if(x [i] == 1)
                            y = i[4:0];
                end
                else
                    y = 0;
        end
endmodule

DigitalCircuitsExperiments/DCE02/encode_32to5_for/obj_dir/dump.vcd
$version Generated by VerilatedVcd $end
$timescale 1s $end

 $scope module TOP $end
  $var wire  1 $ en $end
  $var wire 32 # x [31:0] $end
  $var wire  5 % y [4:0] $end
  $scope module encode_32to5_for $end
   $var wire  1 $ en $end
   $var wire 32 & i [31:0] $end
   $var wire 32 # x [31:0] $end
   $var wire  5 % y [4:0] $end
  $upscope $end
 $upscope $end
$enddefinitions $end


#1
b00000000000000000000000000000000 #
0$
b00000 %
b00000000000000000000000000000000 &
#2
b00000000000000000000000000000001 #
#3
b00000000000000000000000000000010 #
#4
b00000000000000000000000000000100 #
#5
b00000000000000000000000000001000 #
#6
b00000000000000000000000000010000 #
#7
b00000000000000000000000000100000 #
#8
b00000000000000000000000001000000 #
#9
b00000000000000000000000010000000 #
#10
b00000000000000000000000100000000 #
#11
b00000000000000000000001000000000 #
#12
b00000000000000000000010000000000 #
#13
b00000000000000000000100000000000 #
#14
b00000000000000000001000000000000 #
#15
b00000000000000000010000000000000 #
#16
b00000000000000000100000000000000 #
#17
b00000000000000001000000000000000 #
#18
b00000000000000010000000000000000 #
#19
b00000000000000100000000000000000 #
#20
b00000000000001000000000000000000 #
#21
b00000000000010000000000000000000 #
#22
b00000000000100000000000000000000 #
#23
b00000000001000000000000000000000 #
#24
b00000000010000000000000000000000 #
#25
b00000000100000000000000000000000 #
#26
b00000001000000000000000000000000 #
#27
b00000010000000000000000000000000 #
#28
b00000100000000000000000000000000 #
#29
b00001000000000000000000000000000 #
#30
b00010000000000000000000000000000 #
#31
b00100000000000000000000000000000 #
#32
b01000000000000000000000000000000 #
#33
b10000000000000000000000000000000 #
#34
b00000000000000000000000000000000 #
1$
b00000000000000000000000000100000 &
#35
b00000000000000000000000000000001 #
#36
b00000000000000000000000000000010 #
b00001 %
#37
b00000000000000000000000000000100 #
b00010 %
#38
b00000000000000000000000000001000 #
b00011 %
#39
b00000000000000000000000000010000 #
b00100 %
#40
b00000000000000000000000000100000 #
b00101 %
#41
b00000000000000000000000001000000 #
b00110 %
#42
b00000000000000000000000010000000 #
b00111 %
#43
b00000000000000000000000100000000 #
b01000 %
#44
b00000000000000000000001000000000 #
b01001 %
#45
b00000000000000000000010000000000 #
b01010 %
#46
b00000000000000000000100000000000 #
b01011 %
#47
b00000000000000000001000000000000 #
b01100 %
#48
b00000000000000000010000000000000 #
b01101 %
#49
b00000000000000000100000000000000 #
b01110 %
#50
b00000000000000001000000000000000 #
b01111 %
#51
b00000000000000010000000000000000 #
b10000 %
#52
b00000000000000100000000000000000 #
b10001 %
#53
b00000000000001000000000000000000 #
b10010 %
#54
b00000000000010000000000000000000 #
b10011 %
#55
b00000000000100000000000000000000 #
b10100 %
#56
b00000000001000000000000000000000 #
b10101 %
#57
b00000000010000000000000000000000 #
b10110 %
#58
b00000000100000000000000000000000 #
b10111 %
#59
b00000001000000000000000000000000 #
b11000 %
#60
b00000010000000000000000000000000 #
b11001 %
#61
b00000100000000000000000000000000 #
b11010 %
#62
b00001000000000000000000000000000 #
b11011 %
#63
b00010000000000000000000000000000 #
b11100 %
#64
b00100000000000000000000000000000 #
b11101 %
#65
b01000000000000000000000000000000 #
b11110 %
#66
b10000000000000000000000000000000 #
b11111 %
