DigitalCircuitsExperiments/DCE06/LogicLeftShiftRegister_NegEdge_4Bit/LogicLeftShiftRegister_NegEdge_4Bit.v
module LogicLeftShiftRegister_NegEdge_4Bit (clock, reset, D, Q);
    input clock;
    input reset;
    input [3:0] D;
    output reg [3:0] Q;

    always @(negedge clock)
    begin
        if (reset)
            Q = 4'b0000;
        else
            Q = Q << 1 ;        
    end
endmodule

DigitalCircuitsExperiments/DCE06/LogicLeftShiftRegister_NegEdge_4Bit/obj_dir/dump.vcd
$version Generated by VerilatedVcd $end
$date Wed Jan 18 15:12:20 2023 $end
$timescale 1s $end

 $scope module TOP $end
  $var wire  4 % D [3:0] $end
  $var wire  4 & Q [3:0] $end
  $var wire  1 # clock $end
  $var wire  1 $ reset $end
  $scope module LogicLeftShiftRegister_NegEdge_4Bit $end
   $var wire  4 % D [3:0] $end
   $var wire  4 & Q [3:0] $end
   $var wire  1 # clock $end
   $var wire  1 $ reset $end
  $upscope $end
 $upscope $end
$enddefinitions $end


#1
0#
0$
b0000 %
b0000 &
#2
1#
#3
0#
#4
1#
#5
0#
b0001 %
#6
1#
#7
0#
#8
1#
#9
0#
b0010 %
#10
1#
#11
0#
#12
1#
#13
0#
b0011 %
#14
1#
#15
0#
#16
1#
#17
0#
b0100 %
#18
1#
#19
0#
#20
1#
#21
0#
b0101 %
#22
1#
#23
0#
#24
1#
#25
0#
b0110 %
#26
1#
#27
0#
#28
1#
#29
0#
b0111 %
#30
1#
#31
0#
#32
1#
#33
0#
b1000 %
#34
1#
#35
0#
#36
1#
#37
0#
b1001 %
#38
1#
#39
0#
#40
1#
#41
0#
b1010 %
#42
1#
#43
0#
#44
1#
#45
0#
b1011 %
#46
1#
#47
0#
#48
1#
#49
0#
b1100 %
#50
1#
#51
0#
#52
1#
#53
0#
b1101 %
#54
1#
#55
0#
#56
1#
#57
0#
b1110 %
#58
1#
#59
0#
#60
1#
#61
0#
b1111 %
#62
1#
#63
0#
#64
1#
#65
0#
1$
b0000 %
#66
1#
#67
0#
#68
1#
#69
0#
b0001 %
#70
1#
#71
0#
#72
1#
#73
0#
b0010 %
#74
1#
#75
0#
#76
1#
#77
0#
b0011 %
#78
1#
#79
0#
#80
1#
#81
0#
b0100 %
#82
1#
#83
0#
#84
1#
#85
0#
b0101 %
#86
1#
#87
0#
#88
1#
#89
0#
b0110 %
#90
1#
#91
0#
#92
1#
#93
0#
b0111 %
#94
1#
#95
0#
#96
1#
#97
0#
b1000 %
#98
1#
#99
0#
#100
1#
#101
0#
b1001 %
#102
1#
#103
0#
#104
1#
#105
0#
b1010 %
#106
1#
#107
0#
#108
1#
#109
0#
b1011 %
#110
1#
#111
0#
#112
1#
#113
0#
b1100 %
#114
1#
#115
0#
#116
1#
#117
0#
b1101 %
#118
1#
#119
0#
#120
1#
#121
0#
b1110 %
#122
1#
#123
0#
#124
1#
#125
0#
b1111 %
#126
1#
#127
0#
#128
1#
#129
0$
b0000 %
#130
0#
#131
1#
#132
0#
#133
1#
b0001 %
#134
0#
#135
1#
#136
0#
#137
1#
b0010 %
#138
0#
#139
1#
#140
0#
#141
1#
b0011 %
#142
0#
#143
1#
#144
0#
#145
1#
b0100 %
#146
0#
#147
1#
#148
0#
#149
1#
b0101 %
#150
0#
#151
1#
#152
0#
#153
1#
b0110 %
#154
0#
#155
1#
#156
0#
#157
1#
b0111 %
#158
0#
#159
1#
#160
0#
#161
1#
b1000 %
#162
0#
#163
1#
#164
0#
#165
1#
b1001 %
#166
0#
#167
1#
#168
0#
#169
1#
b1010 %
#170
0#
#171
1#
#172
0#
#173
1#
b1011 %
#174
0#
#175
1#
#176
0#
#177
1#
b1100 %
#178
0#
#179
1#
#180
0#
#181
1#
b1101 %
#182
0#
#183
1#
#184
0#
#185
1#
b1110 %
#186
0#
#187
1#
#188
0#
#189
1#
b1111 %
#190
0#
#191
1#
#192
0#
#193
1#
1$
b0000 %
#194
0#
#195
1#
#196
0#
#197
1#
b0001 %
#198
0#
#199
1#
#200
0#
#201
1#
b0010 %
#202
0#
#203
1#
#204
0#
#205
1#
b0011 %
#206
0#
#207
1#
#208
0#
#209
1#
b0100 %
#210
0#
#211
1#
#212
0#
#213
1#
b0101 %
#214
0#
#215
1#
#216
0#
#217
1#
b0110 %
#218
0#
#219
1#
#220
0#
#221
1#
b0111 %
#222
0#
#223
1#
#224
0#
#225
1#
b1000 %
#226
0#
#227
1#
#228
0#
#229
1#
b1001 %
#230
0#
#231
1#
#232
0#
#233
1#
b1010 %
#234
0#
#235
1#
#236
0#
#237
1#
b1011 %
#238
0#
#239
1#
#240
0#
#241
1#
b1100 %
#242
0#
#243
1#
#244
0#
#245
1#
b1101 %
#246
0#
#247
1#
#248
0#
#249
1#
b1110 %
#250
0#
#251
1#
#252
0#
#253
1#
b1111 %
