DigitalCircuitsExperiments/DCE02/decode_5to32_for/decode_5to32_for.v
module decode_5to32_for (x, en, y);
    input [4:0] x;
    input en;
    output reg [31:0] y;
    integer i;
    always @(x or en)
    begin
        if (en)
        begin
            /* verilator lint_off WIDTH */
            for (i=0; i <= 31; i = i + 1)
                if (x == i) 
                    y[i] = 1;
                else
                    y[i] = 0;
            /* verilator lint_on WIDTH */
        end
        else
            y = 32'b00000000000000000000000000000000;
    end
endmodule

DigitalCircuitsExperiments/DCE02/decode_5to32_for/obj_dir/dump.vcd
$version Generated by VerilatedVcd $end
$timescale 1s $end

 $scope module TOP $end
  $var wire  1 $ en $end
  $var wire  5 # x [4:0] $end
  $var wire 32 % y [31:0] $end
  $scope module decode_5to32_for $end
   $var wire  1 $ en $end
   $var wire 32 & i [31:0] $end
   $var wire  5 # x [4:0] $end
   $var wire 32 % y [31:0] $end
  $upscope $end
 $upscope $end
$enddefinitions $end


#1
b00000 #
0$
b00000000000000000000000000000000 %
b00000000000000000000000000000000 &
#2
b00001 #
#3
b00010 #
#4
b00011 #
#5
b00100 #
#6
b00101 #
#7
b00110 #
#8
b00111 #
#9
b01000 #
#10
b01001 #
#11
b01010 #
#12
b01011 #
#13
b01100 #
#14
b01101 #
#15
b01110 #
#16
b01111 #
#17
b10000 #
#18
b10001 #
#19
b10010 #
#20
b10011 #
#21
b10100 #
#22
b10101 #
#23
b10110 #
#24
b10111 #
#25
b11000 #
#26
b11001 #
#27
b11010 #
#28
b11011 #
#29
b11100 #
#30
b11101 #
#31
b11110 #
#32
b11111 #
#33
b00000 #
1$
b00000000000000000000000000000001 %
b00000000000000000000000000100000 &
#34
b00001 #
b00000000000000000000000000000010 %
#35
b00010 #
b00000000000000000000000000000100 %
#36
b00011 #
b00000000000000000000000000001000 %
#37
b00100 #
b00000000000000000000000000010000 %
#38
b00101 #
b00000000000000000000000000100000 %
#39
b00110 #
b00000000000000000000000001000000 %
#40
b00111 #
b00000000000000000000000010000000 %
#41
b01000 #
b00000000000000000000000100000000 %
#42
b01001 #
b00000000000000000000001000000000 %
#43
b01010 #
b00000000000000000000010000000000 %
#44
b01011 #
b00000000000000000000100000000000 %
#45
b01100 #
b00000000000000000001000000000000 %
#46
b01101 #
b00000000000000000010000000000000 %
#47
b01110 #
b00000000000000000100000000000000 %
#48
b01111 #
b00000000000000001000000000000000 %
#49
b10000 #
b00000000000000010000000000000000 %
#50
b10001 #
b00000000000000100000000000000000 %
#51
b10010 #
b00000000000001000000000000000000 %
#52
b10011 #
b00000000000010000000000000000000 %
#53
b10100 #
b00000000000100000000000000000000 %
#54
b10101 #
b00000000001000000000000000000000 %
#55
b10110 #
b00000000010000000000000000000000 %
#56
b10111 #
b00000000100000000000000000000000 %
#57
b11000 #
b00000001000000000000000000000000 %
#58
b11001 #
b00000010000000000000000000000000 %
#59
b11010 #
b00000100000000000000000000000000 %
#60
b11011 #
b00001000000000000000000000000000 %
#61
b11100 #
b00010000000000000000000000000000 %
#62
b11101 #
b00100000000000000000000000000000 %
#63
b11110 #
b01000000000000000000000000000000 %
#64
b11111 #
b10000000000000000000000000000000 %
