DigitalCircuitsExperiments/DCE06/BarrelShifter/BarrelShifter_8Bit/mux41.v
module mux41(datain0, datain1, datain2, datain3, sel0, sel1, dataout);
    input datain0, datain1, datain2, datain3;
    input sel0, sel1;
    output reg dataout;

    always @(sel0 , sel1) 
    begin
        case (sel1)
        0 : case (sel0)
            0 : dataout = datain0;
            1 : dataout = datain1;
            endcase
        1 : case (sel0)
            0 : dataout = datain2;
            1 : dataout = datain3;
            endcase
        endcase
    end

endmodule

DigitalCircuitsExperiments/DCE06/BarrelShifter8/mux21.v
module mux21(datain0, datain1, sel, dataout);
    input datain0, datain1;
    input sel;
    output reg dataout;

    always @(sel) 
    begin
        case (sel)
        0 : dataout = datain0;
        1 : dataout = datain1;
        endcase
    end
endmodule

DigitalCircuitsExperiments/DCE06/BarrelShifter8_Structure/BarrelShifter8_Structure.v
module BarrelShifter8_Structure(din, shamt, lr, al, dout);
    input [7:0] din;
    input [2:0] shamt;
    input lr, al;
    output [7:0] dout;

    wire mc_out, m7a_out, m6a_out, m5a_out, m4a_out, m3a_out, m2a_out, m1a_out, m0a_out;
    wire m7b_out, m6b_out, m5b_out, m4b_out, m3b_out, m2b_out, m1b_out, m0b_out;

    mux21 mc(.datain1(din[7]), .datain0(0), .sel(al), .dataout(mc_out));
    mux41 m7a(.datain0(din[7]), .datain1(mc_out), .datain2(din[7]), .datain3(din[6]), .dataout(m7a_out), .sel0(shamt[0]), .sel1(lr));
    mux41 m6a(.datain0(din[6]), .datain1(din[7]), .datain2(din[6]), .datain3(din[5]), .dataout(m6a_out), .sel0(shamt[0]), .sel1(lr));
    mux41 m5a(.datain0(din[5]), .datain1(din[6]), .datain2(din[5]), .datain3(din[4]), .dataout(m5a_out), .sel0(shamt[0]), .sel1(lr));
    mux41 m4a(.datain0(din[4]), .datain1(din[5]), .datain2(din[4]), .datain3(din[3]), .dataout(m4a_out), .sel0(shamt[0]), .sel1(lr));
    mux41 m3a(.datain0(din[3]), .datain1(din[4]), .datain2(din[3]), .datain3(din[2]), .dataout(m3a_out), .sel0(shamt[0]), .sel1(lr));
    mux41 m2a(.datain0(din[2]), .datain1(din[3]), .datain2(din[2]), .datain3(din[1]), .dataout(m2a_out), .sel0(shamt[0]), .sel1(lr));
    mux41 m1a(.datain0(din[1]), .datain1(din[2]), .datain2(din[1]), .datain3(din[0]), .dataout(m1a_out), .sel0(shamt[0]), .sel1(lr));
    mux41 m0a(.datain0(din[0]), .datain1(din[1]), .datain2(din[0]), .datain3(0), .dataout(m0a_out), .sel0(shamt[0]), .sel1(lr));

    mux41 m7b(.datain0(m7a_out), .datain1(mc_out), .datain2(m7a_out), .datain3(m5a_out), .dataout(m7b_out), .sel0(shamt[1]), .sel1(lr));
    mux41 m6b(.datain0(m6a_out), .datain1(mc_out), .datain2(m6a_out), .datain3(m4a_out), .dataout(m6b_out), .sel0(shamt[1]), .sel1(lr));
    mux41 m5b(.datain0(m5a_out), .datain1(m7a_out), .datain2(m5a_out), .datain3(m3a_out), .dataout(m5b_out), .sel0(shamt[1]), .sel1(lr));
    mux41 m4b(.datain0(m4a_out), .datain1(m6a_out), .datain2(m4a_out), .datain3(m2a_out), .dataout(m4b_out), .sel0(shamt[1]), .sel1(lr));
    mux41 m3b(.datain0(m3a_out), .datain1(m5a_out), .datain2(m3a_out), .datain3(m1a_out), .dataout(m3b_out), .sel0(shamt[1]), .sel1(lr));
    mux41 m2b(.datain0(m2a_out), .datain1(m4a_out), .datain2(m2a_out), .datain3(m0a_out), .dataout(m2b_out), .sel0(shamt[1]), .sel1(lr));
    mux41 m1b(.datain0(m1a_out), .datain1(m3a_out), .datain2(m1a_out), .datain3(0), .dataout(m1b_out), .sel0(shamt[1]), .sel1(lr));
    mux41 m0b(.datain0(m0a_out), .datain1(m2a_out), .datain2(m0a_out), .datain3(0), .dataout(m0b_out), .sel0(shamt[1]), .sel1(lr));

    mux41 m7c(.datain0(m7b_out), .datain1(mc_out), .datain2(m7b_out), .datain3(m7b_out), .dataout(dout[7]), .sel0(shamt[2]), .sel1(lr));
    mux41 m6c(.datain0(m6b_out), .datain1(mc_out), .datain2(m6b_out), .datain3(0), .dataout(dout[6]), .sel0(shamt[2]), .sel1(lr));
    mux41 m5c(.datain0(m5b_out), .datain1(mc_out), .datain2(m5b_out), .datain3(m1b_out), .dataout(dout[5]), .sel0(shamt[2]), .sel1(lr));
    mux41 m4c(.datain0(m4b_out), .datain1(mc_out), .datain2(m4b_out), .datain3(m0b_out), .dataout(dout[4]), .sel0(shamt[2]), .sel1(lr));
    mux41 m3c(.datain0(m3b_out), .datain1(m7b_out), .datain2(m3b_out), .datain3(0), .dataout(dout[3]), .sel0(shamt[2]), .sel1(lr));
    mux41 m2c(.datain0(m2b_out), .datain1(m6b_out), .datain2(m2b_out), .datain3(0), .dataout(dout[2]), .sel0(shamt[2]), .sel1(lr));
    mux41 m1c(.datain0(m1b_out), .datain1(m5b_out), .datain2(m1b_out), .datain3(0), .dataout(dout[1]), .sel0(shamt[2]), .sel1(lr));
    mux41 m0c(.datain0(m0b_out), .datain1(m4b_out), .datain2(m0b_out), .datain3(0), .dataout(dout[0]), .sel0(shamt[2]), .sel1(lr));

endmodule

DigitalCircuitsExperiments/DCE06/BarrelShifter8_Structure/obj_dir/dump.vcd
$version Generated by VerilatedVcd $end
$date Wed Jan 11 18:18:01 2023 $end
$timescale 1s $end

 $scope module TOP $end
  $var wire  1 ? al $end
  $var wire  8 < din [7:0] $end
  $var wire  8 @ dout [7:0] $end
  $var wire  1 > lr $end
  $var wire  3 = shamt [2:0] $end
  $scope module BarrelShifter8_Structure $end
   $var wire  1 ? al $end
   $var wire  8 < din [7:0] $end
   $var wire  8 @ dout [7:0] $end
   $var wire  1 > lr $end
   $var wire  1 + m0a_out $end
   $var wire  1 3 m0b_out $end
   $var wire  1 * m1a_out $end
   $var wire  1 2 m1b_out $end
   $var wire  1 ) m2a_out $end
   $var wire  1 1 m2b_out $end
   $var wire  1 ( m3a_out $end
   $var wire  1 0 m3b_out $end
   $var wire  1 ' m4a_out $end
   $var wire  1 / m4b_out $end
   $var wire  1 & m5a_out $end
   $var wire  1 . m5b_out $end
   $var wire  1 % m6a_out $end
   $var wire  1 - m6b_out $end
   $var wire  1 $ m7a_out $end
   $var wire  1 , m7b_out $end
   $var wire  1 # mc_out $end
   $var wire  3 = shamt [2:0] $end
   $scope module m0a $end
    $var wire  1 I datain0 $end
    $var wire  1 H datain1 $end
    $var wire  1 I datain2 $end
    $var wire  1 L datain3 $end
    $var wire  1 + dataout $end
    $var wire  1 C sel0 $end
    $var wire  1 > sel1 $end
   $upscope $end
   $scope module m0b $end
    $var wire  1 + datain0 $end
    $var wire  1 ) datain1 $end
    $var wire  1 + datain2 $end
    $var wire  1 L datain3 $end
    $var wire  1 3 dataout $end
    $var wire  1 J sel0 $end
    $var wire  1 > sel1 $end
   $upscope $end
   $scope module m0c $end
    $var wire  1 3 datain0 $end
    $var wire  1 / datain1 $end
    $var wire  1 3 datain2 $end
    $var wire  1 L datain3 $end
    $var wire  1 ; dataout $end
    $var wire  1 K sel0 $end
    $var wire  1 > sel1 $end
   $upscope $end
   $scope module m1a $end
    $var wire  1 H datain0 $end
    $var wire  1 G datain1 $end
    $var wire  1 H datain2 $end
    $var wire  1 I datain3 $end
    $var wire  1 * dataout $end
    $var wire  1 C sel0 $end
    $var wire  1 > sel1 $end
   $upscope $end
   $scope module m1b $end
    $var wire  1 * datain0 $end
    $var wire  1 ( datain1 $end
    $var wire  1 * datain2 $end
    $var wire  1 L datain3 $end
    $var wire  1 2 dataout $end
    $var wire  1 J sel0 $end
    $var wire  1 > sel1 $end
   $upscope $end
   $scope module m1c $end
    $var wire  1 2 datain0 $end
    $var wire  1 . datain1 $end
    $var wire  1 2 datain2 $end
    $var wire  1 L datain3 $end
    $var wire  1 : dataout $end
    $var wire  1 K sel0 $end
    $var wire  1 > sel1 $end
   $upscope $end
   $scope module m2a $end
    $var wire  1 G datain0 $end
    $var wire  1 F datain1 $end
    $var wire  1 G datain2 $end
    $var wire  1 H datain3 $end
    $var wire  1 ) dataout $end
    $var wire  1 C sel0 $end
    $var wire  1 > sel1 $end
   $upscope $end
   $scope module m2b $end
    $var wire  1 ) datain0 $end
    $var wire  1 ' datain1 $end
    $var wire  1 ) datain2 $end
    $var wire  1 + datain3 $end
    $var wire  1 1 dataout $end
    $var wire  1 J sel0 $end
    $var wire  1 > sel1 $end
   $upscope $end
   $scope module m2c $end
    $var wire  1 1 datain0 $end
    $var wire  1 - datain1 $end
    $var wire  1 1 datain2 $end
    $var wire  1 L datain3 $end
    $var wire  1 9 dataout $end
    $var wire  1 K sel0 $end
    $var wire  1 > sel1 $end
   $upscope $end
   $scope module m3a $end
    $var wire  1 F datain0 $end
    $var wire  1 E datain1 $end
    $var wire  1 F datain2 $end
    $var wire  1 G datain3 $end
    $var wire  1 ( dataout $end
    $var wire  1 C sel0 $end
    $var wire  1 > sel1 $end
   $upscope $end
   $scope module m3b $end
    $var wire  1 ( datain0 $end
    $var wire  1 & datain1 $end
    $var wire  1 ( datain2 $end
    $var wire  1 * datain3 $end
    $var wire  1 0 dataout $end
    $var wire  1 J sel0 $end
    $var wire  1 > sel1 $end
   $upscope $end
   $scope module m3c $end
    $var wire  1 0 datain0 $end
    $var wire  1 , datain1 $end
    $var wire  1 0 datain2 $end
    $var wire  1 L datain3 $end
    $var wire  1 8 dataout $end
    $var wire  1 K sel0 $end
    $var wire  1 > sel1 $end
   $upscope $end
   $scope module m4a $end
    $var wire  1 E datain0 $end
    $var wire  1 D datain1 $end
    $var wire  1 E datain2 $end
    $var wire  1 F datain3 $end
    $var wire  1 ' dataout $end
    $var wire  1 C sel0 $end
    $var wire  1 > sel1 $end
   $upscope $end
   $scope module m4b $end
    $var wire  1 ' datain0 $end
    $var wire  1 % datain1 $end
    $var wire  1 ' datain2 $end
    $var wire  1 ) datain3 $end
    $var wire  1 / dataout $end
    $var wire  1 J sel0 $end
    $var wire  1 > sel1 $end
   $upscope $end
   $scope module m4c $end
    $var wire  1 / datain0 $end
    $var wire  1 # datain1 $end
    $var wire  1 / datain2 $end
    $var wire  1 3 datain3 $end
    $var wire  1 7 dataout $end
    $var wire  1 K sel0 $end
    $var wire  1 > sel1 $end
   $upscope $end
   $scope module m5a $end
    $var wire  1 D datain0 $end
    $var wire  1 B datain1 $end
    $var wire  1 D datain2 $end
    $var wire  1 E datain3 $end
    $var wire  1 & dataout $end
    $var wire  1 C sel0 $end
    $var wire  1 > sel1 $end
   $upscope $end
   $scope module m5b $end
    $var wire  1 & datain0 $end
    $var wire  1 $ datain1 $end
    $var wire  1 & datain2 $end
    $var wire  1 ( datain3 $end
    $var wire  1 . dataout $end
    $var wire  1 J sel0 $end
    $var wire  1 > sel1 $end
   $upscope $end
   $scope module m5c $end
    $var wire  1 . datain0 $end
    $var wire  1 # datain1 $end
    $var wire  1 . datain2 $end
    $var wire  1 2 datain3 $end
    $var wire  1 6 dataout $end
    $var wire  1 K sel0 $end
    $var wire  1 > sel1 $end
   $upscope $end
   $scope module m6a $end
    $var wire  1 B datain0 $end
    $var wire  1 A datain1 $end
    $var wire  1 B datain2 $end
    $var wire  1 D datain3 $end
    $var wire  1 % dataout $end
    $var wire  1 C sel0 $end
    $var wire  1 > sel1 $end
   $upscope $end
   $scope module m6b $end
    $var wire  1 % datain0 $end
    $var wire  1 # datain1 $end
    $var wire  1 % datain2 $end
    $var wire  1 ' datain3 $end
    $var wire  1 - dataout $end
    $var wire  1 J sel0 $end
    $var wire  1 > sel1 $end
   $upscope $end
   $scope module m6c $end
    $var wire  1 - datain0 $end
    $var wire  1 # datain1 $end
    $var wire  1 - datain2 $end
    $var wire  1 L datain3 $end
    $var wire  1 5 dataout $end
    $var wire  1 K sel0 $end
    $var wire  1 > sel1 $end
   $upscope $end
   $scope module m7a $end
    $var wire  1 A datain0 $end
    $var wire  1 # datain1 $end
    $var wire  1 A datain2 $end
    $var wire  1 B datain3 $end
    $var wire  1 $ dataout $end
    $var wire  1 C sel0 $end
    $var wire  1 > sel1 $end
   $upscope $end
   $scope module m7b $end
    $var wire  1 $ datain0 $end
    $var wire  1 # datain1 $end
    $var wire  1 $ datain2 $end
    $var wire  1 & datain3 $end
    $var wire  1 , dataout $end
    $var wire  1 J sel0 $end
    $var wire  1 > sel1 $end
   $upscope $end
   $scope module m7c $end
    $var wire  1 , datain0 $end
    $var wire  1 # datain1 $end
    $var wire  1 , datain2 $end
    $var wire  1 , datain3 $end
    $var wire  1 4 dataout $end
    $var wire  1 K sel0 $end
    $var wire  1 > sel1 $end
   $upscope $end
   $scope module mc $end
    $var wire  1 L datain0 $end
    $var wire  1 A datain1 $end
    $var wire  1 # dataout $end
    $var wire  1 ? sel $end
   $upscope $end
  $upscope $end
 $upscope $end
$enddefinitions $end


#1
0#
0$
0%
0&
0'
0(
0)
0*
0+
0,
0-
0.
0/
00
01
02
03
04
05
06
07
08
09
0:
0;
b00000000 <
b000 =
0>
0?
b00000000 @
0A
0B
0C
0D
0E
0F
0G
0H
0I
0J
0K
0L
#2
1+
13
1;
b00000001 <
b00000001 @
1I
#3
1*
0+
12
03
1:
0;
b00000010 <
b00000010 @
1H
0I
#4
1+
13
1;
b00000011 <
b00000011 @
1I
#5
1)
0*
0+
11
02
03
19
0:
0;
b00000100 <
b00000100 @
1G
0H
0I
#6
1+
13
1;
b00000101 <
b00000101 @
1I
#7
1*
0+
12
03
1:
0;
b00000110 <
b00000110 @
1H
0I
#8
1+
13
1;
b00000111 <
b00000111 @
1I
#9
1(
0)
0*
0+
10
01
02
03
18
09
0:
0;
b00001000 <
b00001000 @
1F
0G
0H
0I
#10
1+
13
1;
b00001001 <
b00001001 @
1I
#11
1*
0+
12
03
1:
0;
b00001010 <
b00001010 @
1H
0I
#12
1+
13
1;
b00001011 <
b00001011 @
1I
#13
1)
0*
0+
11
02
03
19
0:
0;
b00001100 <
b00001100 @
1G
0H
0I
#14
1+
13
1;
b00001101 <
b00001101 @
1I
#15
1*
0+
12
03
1:
0;
b00001110 <
b00001110 @
1H
0I
#16
1+
13
1;
b00001111 <
b00001111 @
1I
#17
1'
0(
0)
0*
0+
1/
00
01
02
03
17
08
09
0:
0;
b00010000 <
b00010000 @
1E
0F
0G
0H
0I
#18
1+
13
1;
b00010001 <
b00010001 @
1I
#19
1*
0+
12
03
1:
0;
b00010010 <
b00010010 @
1H
0I
#20
1+
13
1;
b00010011 <
b00010011 @
1I
#21
1)
0*
0+
11
02
03
19
0:
0;
b00010100 <
b00010100 @
1G
0H
0I
#22
1+
13
1;
b00010101 <
b00010101 @
1I
#23
1*
0+
12
03
1:
0;
b00010110 <
b00010110 @
1H
0I
#24
1+
13
1;
b00010111 <
b00010111 @
1I
#25
1(
0)
0*
0+
10
01
02
03
18
09
0:
0;
b00011000 <
b00011000 @
1F
0G
0H
0I
#26
1+
13
1;
b00011001 <
b00011001 @
1I
#27
1*
0+
12
03
1:
0;
b00011010 <
b00011010 @
1H
0I
#28
1+
13
1;
b00011011 <
b00011011 @
1I
#29
1)
0*
0+
11
02
03
19
0:
0;
b00011100 <
b00011100 @
1G
0H
0I
#30
1+
13
1;
b00011101 <
b00011101 @
1I
#31
1*
0+
12
03
1:
0;
b00011110 <
b00011110 @
1H
0I
#32
1+
13
1;
b00011111 <
b00011111 @
1I
#33
1&
0'
0(
0)
0*
0+
1.
0/
00
01
02
03
16
07
08
09
0:
0;
b00100000 <
b00100000 @
1D
0E
0F
0G
0H
0I
#34
1+
13
1;
b00100001 <
b00100001 @
1I
#35
1*
0+
12
03
1:
0;
b00100010 <
b00100010 @
1H
0I
#36
1+
13
1;
b00100011 <
b00100011 @
1I
#37
1)
0*
0+
11
02
03
19
0:
0;
b00100100 <
b00100100 @
1G
0H
0I
#38
1+
13
1;
b00100101 <
b00100101 @
1I
#39
1*
0+
12
03
1:
0;
b00100110 <
b00100110 @
1H
0I
#40
1+
13
1;
b00100111 <
b00100111 @
1I
#41
1(
0)
0*
0+
10
01
02
03
18
09
0:
0;
b00101000 <
b00101000 @
1F
0G
0H
0I
#42
1+
13
1;
b00101001 <
b00101001 @
1I
#43
1*
0+
12
03
1:
0;
b00101010 <
b00101010 @
1H
0I
#44
1+
13
1;
b00101011 <
b00101011 @
1I
#45
1)
0*
0+
11
02
03
19
0:
0;
b00101100 <
b00101100 @
1G
0H
0I
#46
1+
13
1;
b00101101 <
b00101101 @
1I
#47
1*
0+
12
03
1:
0;
b00101110 <
b00101110 @
1H
0I
#48
1+
13
1;
b00101111 <
b00101111 @
1I
#49
1'
0(
0)
0*
0+
1/
00
01
02
03
17
08
09
0:
0;
b00110000 <
b00110000 @
1E
0F
0G
0H
0I
#50
1+
13
1;
b00110001 <
b00110001 @
1I
#51
1*
0+
12
03
1:
0;
b00110010 <
b00110010 @
1H
0I
#52
1+
13
1;
b00110011 <
b00110011 @
1I
#53
1)
0*
0+
11
02
03
19
0:
0;
b00110100 <
b00110100 @
1G
0H
0I
#54
1+
13
1;
b00110101 <
b00110101 @
1I
#55
1*
0+
12
03
1:
0;
b00110110 <
b00110110 @
1H
0I
#56
1+
13
1;
b00110111 <
b00110111 @
1I
#57
1(
0)
0*
0+
10
01
02
03
18
09
0:
0;
b00111000 <
b00111000 @
1F
0G
0H
0I
#58
1+
13
1;
b00111001 <
b00111001 @
1I
#59
1*
0+
12
03
1:
0;
b00111010 <
b00111010 @
1H
0I
#60
1+
13
1;
b00111011 <
b00111011 @
1I
#61
1)
0*
0+
11
02
03
19
0:
0;
b00111100 <
b00111100 @
1G
0H
0I
#62
1+
13
1;
b00111101 <
b00111101 @
1I
#63
1*
0+
12
03
1:
0;
b00111110 <
b00111110 @
1H
0I
#64
1+
13
1;
b00111111 <
b00111111 @
1I
#65
1%
0&
0'
0(
0)
0*
0+
1-
0.
0/
00
01
02
03
15
06
07
08
09
0:
0;
b01000000 <
b01000000 @
1B
0D
0E
0F
0G
0H
0I
#66
1+
13
1;
b01000001 <
b01000001 @
1I
#67
1*
0+
12
03
1:
0;
b01000010 <
b01000010 @
1H
0I
#68
1+
13
1;
b01000011 <
b01000011 @
1I
#69
1)
0*
0+
11
02
03
19
0:
0;
b01000100 <
b01000100 @
1G
0H
0I
#70
1+
13
1;
b01000101 <
b01000101 @
1I
#71
1*
0+
12
03
1:
0;
b01000110 <
b01000110 @
1H
0I
#72
1+
13
1;
b01000111 <
b01000111 @
1I
#73
1(
0)
0*
0+
10
01
02
03
18
09
0:
0;
b01001000 <
b01001000 @
1F
0G
0H
0I
#74
1+
13
1;
b01001001 <
b01001001 @
1I
#75
1*
0+
12
03
1:
0;
b01001010 <
b01001010 @
1H
0I
#76
1+
13
1;
b01001011 <
b01001011 @
1I
#77
1)
0*
0+
11
02
03
19
0:
0;
b01001100 <
b01001100 @
1G
0H
0I
#78
1+
13
1;
b01001101 <
b01001101 @
1I
#79
1*
0+
12
03
1:
0;
b01001110 <
b01001110 @
1H
0I
#80
1+
13
1;
b01001111 <
b01001111 @
1I
#81
1'
0(
0)
0*
0+
1/
00
01
02
03
17
08
09
0:
0;
b01010000 <
b01010000 @
1E
0F
0G
0H
0I
#82
1+
13
1;
b01010001 <
b01010001 @
1I
#83
1*
0+
12
03
1:
0;
b01010010 <
b01010010 @
1H
0I
#84
1+
13
1;
b01010011 <
b01010011 @
1I
#85
1)
0*
0+
11
02
03
19
0:
0;
b01010100 <
b01010100 @
1G
0H
0I
#86
1+
13
1;
b01010101 <
b01010101 @
1I
#87
1*
0+
12
03
1:
0;
b01010110 <
b01010110 @
1H
0I
#88
1+
13
1;
b01010111 <
b01010111 @
1I
#89
1(
0)
0*
0+
10
01
02
03
18
09
0:
0;
b01011000 <
b01011000 @
1F
0G
0H
0I
#90
1+
13
1;
b01011001 <
b01011001 @
1I
#91
1*
0+
12
03
1:
0;
b01011010 <
b01011010 @
1H
0I
#92
1+
13
1;
b01011011 <
b01011011 @
1I
#93
1)
0*
0+
11
02
03
19
0:
0;
b01011100 <
b01011100 @
1G
0H
0I
#94
1+
13
1;
b01011101 <
b01011101 @
1I
#95
1*
0+
12
03
1:
0;
b01011110 <
b01011110 @
1H
0I
#96
1+
13
1;
b01011111 <
b01011111 @
1I
#97
1&
0'
0(
0)
0*
0+
1.
0/
00
01
02
03
16
07
08
09
0:
0;
b01100000 <
b01100000 @
1D
0E
0F
0G
0H
0I
#98
1+
13
1;
b01100001 <
b01100001 @
1I
#99
1*
0+
12
03
1:
0;
b01100010 <
b01100010 @
1H
0I
#100
1+
13
1;
b01100011 <
b01100011 @
1I
#101
1)
0*
0+
11
02
03
19
0:
0;
b01100100 <
b01100100 @
1G
0H
0I
#102
1+
13
1;
b01100101 <
b01100101 @
1I
#103
1*
0+
12
03
1:
0;
b01100110 <
b01100110 @
1H
0I
#104
1+
13
1;
b01100111 <
b01100111 @
1I
#105
1(
0)
0*
0+
10
01
02
03
18
09
0:
0;
b01101000 <
b01101000 @
1F
0G
0H
0I
#106
1+
13
1;
b01101001 <
b01101001 @
1I
#107
1*
0+
12
03
1:
0;
b01101010 <
b01101010 @
1H
0I
#108
1+
13
1;
b01101011 <
b01101011 @
1I
#109
1)
0*
0+
11
02
03
19
0:
0;
b01101100 <
b01101100 @
1G
0H
0I
#110
1+
13
1;
b01101101 <
b01101101 @
1I
#111
1*
0+
12
03
1:
0;
b01101110 <
b01101110 @
1H
0I
#112
1+
13
1;
b01101111 <
b01101111 @
1I
#113
1'
0(
0)
0*
0+
1/
00
01
02
03
17
08
09
0:
0;
b01110000 <
b01110000 @
1E
0F
0G
0H
0I
#114
1+
13
1;
b01110001 <
b01110001 @
1I
#115
1*
0+
12
03
1:
0;
b01110010 <
b01110010 @
1H
0I
#116
1+
13
1;
b01110011 <
b01110011 @
1I
#117
1)
0*
0+
11
02
03
19
0:
0;
b01110100 <
b01110100 @
1G
0H
0I
#118
1+
13
1;
b01110101 <
b01110101 @
1I
#119
1*
0+
12
03
1:
0;
b01110110 <
b01110110 @
1H
0I
#120
1+
13
1;
b01110111 <
b01110111 @
1I
#121
1(
0)
0*
0+
10
01
02
03
18
09
0:
0;
b01111000 <
b01111000 @
1F
0G
0H
0I
#122
1+
13
1;
b01111001 <
b01111001 @
1I
#123
1*
0+
12
03
1:
0;
b01111010 <
b01111010 @
1H
0I
#124
1+
13
1;
b01111011 <
b01111011 @
1I
#125
1)
0*
0+
11
02
03
19
0:
0;
b01111100 <
b01111100 @
1G
0H
0I
#126
1+
13
1;
b01111101 <
b01111101 @
1I
#127
1*
0+
12
03
1:
0;
b01111110 <
b01111110 @
1H
0I
#128
1+
13
1;
b01111111 <
b01111111 @
1I
#129
1$
0%
0&
0'
0(
0)
0*
0+
1,
0-
0.
0/
00
01
02
03
14
05
06
07
08
09
0:
0;
b10000000 <
b10000000 @
1A
0B
0D
0E
0F
0G
0H
0I
#130
1+
13
1;
b10000001 <
b10000001 @
1I
#131
1*
0+
12
03
1:
0;
b10000010 <
b10000010 @
1H
0I
#132
1+
13
1;
b10000011 <
b10000011 @
1I
#133
1)
0*
0+
11
02
03
19
0:
0;
b10000100 <
b10000100 @
1G
0H
0I
#134
1+
13
1;
b10000101 <
b10000101 @
1I
#135
1*
0+
12
03
1:
0;
b10000110 <
b10000110 @
1H
0I
#136
1+
13
1;
b10000111 <
b10000111 @
1I
#137
1(
0)
0*
0+
10
01
02
03
18
09
0:
0;
b10001000 <
b10001000 @
1F
0G
0H
0I
#138
1+
13
1;
b10001001 <
b10001001 @
1I
#139
1*
0+
12
03
1:
0;
b10001010 <
b10001010 @
1H
0I
#140
1+
13
1;
b10001011 <
b10001011 @
1I
#141
1)
0*
0+
11
02
03
19
0:
0;
b10001100 <
b10001100 @
1G
0H
0I
#142
1+
13
1;
b10001101 <
b10001101 @
1I
#143
1*
0+
12
03
1:
0;
b10001110 <
b10001110 @
1H
0I
#144
1+
13
1;
b10001111 <
b10001111 @
1I
#145
1'
0(
0)
0*
0+
1/
00
01
02
03
17
08
09
0:
0;
b10010000 <
b10010000 @
1E
0F
0G
0H
0I
#146
1+
13
1;
b10010001 <
b10010001 @
1I
#147
1*
0+
12
03
1:
0;
b10010010 <
b10010010 @
1H
0I
#148
1+
13
1;
b10010011 <
b10010011 @
1I
#149
1)
0*
0+
11
02
03
19
0:
0;
b10010100 <
b10010100 @
1G
0H
0I
#150
1+
13
1;
b10010101 <
b10010101 @
1I
#151
1*
0+
12
03
1:
0;
b10010110 <
b10010110 @
1H
0I
#152
1+
13
1;
b10010111 <
b10010111 @
1I
#153
1(
0)
0*
0+
10
01
02
03
18
09
0:
0;
b10011000 <
b10011000 @
1F
0G
0H
0I
#154
1+
13
1;
b10011001 <
b10011001 @
1I
#155
1*
0+
12
03
1:
0;
b10011010 <
b10011010 @
1H
0I
#156
1+
13
1;
b10011011 <
b10011011 @
1I
#157
1)
0*
0+
11
02
03
19
0:
0;
b10011100 <
b10011100 @
1G
0H
0I
#158
1+
13
1;
b10011101 <
b10011101 @
1I
#159
1*
0+
12
03
1:
0;
b10011110 <
b10011110 @
1H
0I
#160
1+
13
1;
b10011111 <
b10011111 @
1I
#161
1&
0'
0(
0)
0*
0+
1.
0/
00
01
02
03
16
07
08
09
0:
0;
b10100000 <
b10100000 @
1D
0E
0F
0G
0H
0I
#162
1+
13
1;
b10100001 <
b10100001 @
1I
#163
1*
0+
12
03
1:
0;
b10100010 <
b10100010 @
1H
0I
#164
1+
13
1;
b10100011 <
b10100011 @
1I
#165
1)
0*
0+
11
02
03
19
0:
0;
b10100100 <
b10100100 @
1G
0H
0I
#166
1+
13
1;
b10100101 <
b10100101 @
1I
#167
1*
0+
12
03
1:
0;
b10100110 <
b10100110 @
1H
0I
#168
1+
13
1;
b10100111 <
b10100111 @
1I
#169
1(
0)
0*
0+
10
01
02
03
18
09
0:
0;
b10101000 <
b10101000 @
1F
0G
0H
0I
#170
1+
13
1;
b10101001 <
b10101001 @
1I
#171
1*
0+
12
03
1:
0;
b10101010 <
b10101010 @
1H
0I
#172
1+
13
1;
b10101011 <
b10101011 @
1I
#173
1)
0*
0+
11
02
03
19
0:
0;
b10101100 <
b10101100 @
1G
0H
0I
#174
1+
13
1;
b10101101 <
b10101101 @
1I
#175
1*
0+
12
03
1:
0;
b10101110 <
b10101110 @
1H
0I
#176
1+
13
1;
b10101111 <
b10101111 @
1I
#177
1'
0(
0)
0*
0+
1/
00
01
02
03
17
08
09
0:
0;
b10110000 <
b10110000 @
1E
0F
0G
0H
0I
#178
1+
13
1;
b10110001 <
b10110001 @
1I
#179
1*
0+
12
03
1:
0;
b10110010 <
b10110010 @
1H
0I
#180
1+
13
1;
b10110011 <
b10110011 @
1I
#181
1)
0*
0+
11
02
03
19
0:
0;
b10110100 <
b10110100 @
1G
0H
0I
#182
1+
13
1;
b10110101 <
b10110101 @
1I
#183
1*
0+
12
03
1:
0;
b10110110 <
b10110110 @
1H
0I
#184
1+
13
1;
b10110111 <
b10110111 @
1I
#185
1(
0)
0*
0+
10
01
02
03
18
09
0:
0;
b10111000 <
b10111000 @
1F
0G
0H
0I
#186
1+
13
1;
b10111001 <
b10111001 @
1I
#187
1*
0+
12
03
1:
0;
b10111010 <
b10111010 @
1H
0I
#188
1+
13
1;
b10111011 <
b10111011 @
1I
#189
1)
0*
0+
11
02
03
19
0:
0;
b10111100 <
b10111100 @
1G
0H
0I
#190
1+
13
1;
b10111101 <
b10111101 @
1I
#191
1*
0+
12
03
1:
0;
b10111110 <
b10111110 @
1H
0I
#192
1+
13
1;
b10111111 <
b10111111 @
1I
#193
1%
0&
0'
0(
0)
0*
0+
1-
0.
0/
00
01
02
03
15
06
07
08
09
0:
0;
b11000000 <
b11000000 @
1B
0D
0E
0F
0G
0H
0I
#194
1+
13
1;
b11000001 <
b11000001 @
1I
#195
1*
0+
12
03
1:
0;
b11000010 <
b11000010 @
1H
0I
#196
1+
13
1;
b11000011 <
b11000011 @
1I
#197
1)
0*
0+
11
02
03
19
0:
0;
b11000100 <
b11000100 @
1G
0H
0I
#198
1+
13
1;
b11000101 <
b11000101 @
1I
#199
1*
0+
12
03
1:
0;
b11000110 <
b11000110 @
1H
0I
#200
1+
13
1;
b11000111 <
b11000111 @
1I
#201
1(
0)
0*
0+
10
01
02
03
18
09
0:
0;
b11001000 <
b11001000 @
1F
0G
0H
0I
#202
1+
13
1;
b11001001 <
b11001001 @
1I
#203
1*
0+
12
03
1:
0;
b11001010 <
b11001010 @
1H
0I
#204
1+
13
1;
b11001011 <
b11001011 @
1I
#205
1)
0*
0+
11
02
03
19
0:
0;
b11001100 <
b11001100 @
1G
0H
0I
#206
1+
13
1;
b11001101 <
b11001101 @
1I
#207
1*
0+
12
03
1:
0;
b11001110 <
b11001110 @
1H
0I
#208
1+
13
1;
b11001111 <
b11001111 @
1I
#209
1'
0(
0)
0*
0+
1/
00
01
02
03
17
08
09
0:
0;
b11010000 <
b11010000 @
1E
0F
0G
0H
0I
#210
1+
13
1;
b11010001 <
b11010001 @
1I
#211
1*
0+
12
03
1:
0;
b11010010 <
b11010010 @
1H
0I
#212
1+
13
1;
b11010011 <
b11010011 @
1I
#213
1)
0*
0+
11
02
03
19
0:
0;
b11010100 <
b11010100 @
1G
0H
0I
#214
1+
13
1;
b11010101 <
b11010101 @
1I
#215
1*
0+
12
03
1:
0;
b11010110 <
b11010110 @
1H
0I
#216
1+
13
1;
b11010111 <
b11010111 @
1I
#217
1(
0)
0*
0+
10
01
02
03
18
09
0:
0;
b11011000 <
b11011000 @
1F
0G
0H
0I
#218
1+
13
1;
b11011001 <
b11011001 @
1I
#219
1*
0+
12
03
1:
0;
b11011010 <
b11011010 @
1H
0I
