DigitalCircuitsExperiments/DCE06/ArithmeticLeftShiftRegister_NegEdge_8Bit/ArithmeticLeftShiftRegister_NegEdge_8Bit.v
module ArithmeticLeftShiftRegister_NegEdge_8Bit (clock, reset, D, Q);
    input clock;
    input reset;
    input [7:0] D;
    output reg [7:0] Q;

    always @(negedge clock)
    begin
        if (reset)
            Q = 8'b00000000;
        else
            Q = Q << 1 ;        
    end
endmodule

DigitalCircuitsExperiments/DCE06/ArithmeticLeftShiftRegister_NegEdge_8Bit/obj_dir/dump.vcd
$version Generated by VerilatedVcd $end
$date Wed Jan 18 12:13:39 2023 $end
$timescale 1s $end

 $scope module TOP $end
  $var wire  8 % D [7:0] $end
  $var wire  8 & Q [7:0] $end
  $var wire  1 # clock $end
  $var wire  1 $ reset $end
  $scope module ArithmeticLeftShiftRegister_NegEdge_8Bit $end
   $var wire  8 % D [7:0] $end
   $var wire  8 & Q [7:0] $end
   $var wire  1 # clock $end
   $var wire  1 $ reset $end
  $upscope $end
 $upscope $end
$enddefinitions $end


#1
0#
0$
b00000000 %
b00000000 &
#2
1#
#3
0#
#4
1#
#5
0#
b00000001 %
#6
1#
#7
0#
#8
1#
#9
0#
b00000010 %
#10
1#
#11
0#
#12
1#
#13
0#
b00000011 %
#14
1#
#15
0#
#16
1#
#17
0#
b00000100 %
#18
1#
#19
0#
#20
1#
#21
0#
b00000101 %
#22
1#
#23
0#
#24
1#
#25
0#
b00000110 %
#26
1#
#27
0#
#28
1#
#29
0#
b00000111 %
#30
1#
#31
0#
#32
1#
#33
0#
b00001000 %
#34
1#
#35
0#
#36
1#
#37
0#
b00001001 %
#38
1#
#39
0#
#40
1#
#41
0#
b00001010 %
#42
1#
#43
0#
#44
1#
#45
0#
b00001011 %
#46
1#
#47
0#
#48
1#
#49
0#
b00001100 %
#50
1#
#51
0#
#52
1#
#53
0#
b00001101 %
#54
1#
#55
0#
#56
1#
#57
0#
b00001110 %
#58
1#
#59
0#
#60
1#
#61
0#
b00001111 %
#62
1#
#63
0#
#64
1#
#65
0#
b00010000 %
#66
1#
#67
0#
#68
1#
#69
0#
b00010001 %
#70
1#
#71
0#
#72
1#
#73
0#
b00010010 %
#74
1#
#75
0#
#76
1#
#77
0#
b00010011 %
#78
1#
#79
0#
#80
1#
#81
0#
b00010100 %
#82
1#
#83
0#
#84
1#
#85
0#
b00010101 %
#86
1#
#87
0#
#88
1#
#89
0#
b00010110 %
#90
1#
#91
0#
#92
1#
#93
0#
b00010111 %
#94
1#
#95
0#
#96
1#
#97
0#
b00011000 %
#98
1#
#99
0#
#100
1#
#101
0#
b00011001 %
#102
1#
#103
0#
#104
1#
#105
0#
b00011010 %
#106
1#
#107
0#
#108
1#
#109
0#
b00011011 %
#110
1#
#111
0#
#112
1#
#113
0#
b00011100 %
#114
1#
#115
0#
#116
1#
#117
0#
b00011101 %
#118
1#
#119
0#
#120
1#
#121
0#
b00011110 %
#122
1#
#123
0#
#124
1#
#125
0#
b00011111 %
#126
1#
#127
0#
#128
1#
#129
0#
b00100000 %
#130
1#
#131
0#
#132
1#
#133
0#
b00100001 %
#134
1#
#135
0#
#136
1#
#137
0#
b00100010 %
#138
1#
#139
0#
#140
1#
#141
0#
b00100011 %
#142
1#
#143
0#
#144
1#
#145
0#
b00100100 %
#146
1#
#147
0#
#148
1#
#149
0#
b00100101 %
#150
1#
#151
0#
#152
1#
#153
0#
b00100110 %
#154
1#
#155
0#
#156
1#
#157
0#
b00100111 %
#158
1#
#159
0#
#160
1#
#161
0#
b00101000 %
#162
1#
#163
0#
#164
1#
#165
0#
b00101001 %
#166
1#
#167
0#
#168
1#
#169
0#
b00101010 %
#170
1#
#171
0#
#172
1#
#173
0#
b00101011 %
#174
1#
#175
0#
#176
1#
#177
0#
b00101100 %
#178
1#
#179
0#
#180
1#
#181
0#
b00101101 %
#182
1#
#183
0#
#184
1#
#185
0#
b00101110 %
#186
1#
#187
0#
#188
1#
#189
0#
b00101111 %
#190
1#
#191
0#
#192
1#
#193
0#
b00110000 %
#194
1#
#195
0#
#196
1#
#197
0#
b00110001 %
#198
1#
#199
0#
#200
1#
#201
0#
b00110010 %
#202
1#
#203
0#
#204
1#
#205
0#
b00110011 %
#206
1#
#207
0#
#208
1#
#209
0#
b00110100 %
#210
1#
#211
0#
#212
1#
#213
0#
b00110101 %
#214
1#
#215
0#
#216
1#
#217
0#
b00110110 %
#218
1#
#219
0#
#220
1#
#221
0#
b00110111 %
#222
1#
#223
0#
#224
1#
#225
0#
b00111000 %
#226
1#
#227
0#
#228
1#
#229
0#
b00111001 %
#230
1#
#231
0#
#232
1#
#233
0#
b00111010 %
#234
1#
#235
0#
#236
1#
#237
0#
b00111011 %
#238
1#
#239
0#
#240
1#
#241
0#
b00111100 %
#242
1#
#243
0#
#244
1#
#245
0#
b00111101 %
#246
1#
#247
0#
#248
1#
#249
0#
b00111110 %
#250
1#
#251
0#
#252
1#
#253
0#
b00111111 %
#254
1#
#255
0#
#256
1#
#257
0#
b01000000 %
#258
1#
#259
0#
#260
1#
#261
0#
b01000001 %
#262
1#
#263
0#
#264
1#
#265
0#
b01000010 %
#266
1#
#267
0#
#268
1#
#269
0#
b01000011 %
#270
1#
#271
0#
#272
1#
#273
0#
b01000100 %
#274
1#
#275
0#
#276
1#
#277
0#
b01000101 %
#278
1#
#279
0#
#280
1#
#281
0#
b01000110 %
#282
1#
#283
0#
#284
1#
#285
0#
b01000111 %
#286
1#
#287
0#
#288
1#
#289
0#
b01001000 %
#290
1#
#291
0#
#292
1#
#293
0#
b01001001 %
#294
1#
#295
0#
#296
1#
#297
0#
b01001010 %
#298
1#
#299
0#
#300
1#
#301
0#
b01001011 %
#302
1#
#303
0#
#304
1#
#305
0#
b01001100 %
#306
1#
#307
0#
#308
1#
#309
0#
b01001101 %
#310
1#
#311
0#
#312
1#
#313
0#
b01001110 %
#314
1#
#315
0#
#316
1#
#317
0#
b01001111 %
#318
1#
#319
0#
#320
1#
#321
0#
b01010000 %
#322
1#
#323
0#
#324
1#
#325
0#
b01010001 %
#326
1#
#327
0#
#328
1#
#329
0#
b01010010 %
#330
1#
#331
0#
#332
1#
#333
0#
b01010011 %
#334
1#
#335
0#
#336
1#
#337
0#
b01010100 %
#338
1#
#339
0#
#340
1#
#341
0#
b01010101 %
#342
1#
#343
0#
#344
1#
#345
0#
b01010110 %
#346
1#
#347
0#
#348
1#
#349
0#
b01010111 %
#350
1#
#351
0#
#352
1#
#353
0#
b01011000 %
#354
1#
#355
0#
#356
1#
#357
0#
b01011001 %
#358
1#
#359
0#
#360
1#
#361
0#
b01011010 %
#362
1#
#363
0#
#364
1#
#365
0#
b01011011 %
#366
1#
#367
0#
#368
1#
#369
0#
b01011100 %
#370
1#
#371
0#
#372
1#
#373
0#
b01011101 %
#374
1#
#375
0#
#376
1#
#377
0#
b01011110 %
#378
1#
#379
0#
#380
1#
#381
0#
b01011111 %
#382
1#
#383
0#
#384
1#
#385
0#
b01100000 %
#386
1#
#387
0#
#388
1#
#389
0#
b01100001 %
#390
1#
#391
0#
#392
1#
#393
0#
b01100010 %
#394
1#
#395
0#
#396
1#
#397
0#
b01100011 %
#398
1#
#399
0#
#400
1#
#401
0#
b01100100 %
#402
1#
#403
0#
#404
1#
#405
0#
b01100101 %
#406
1#
#407
0#
#408
1#
#409
0#
b01100110 %
#410
1#
#411
0#
#412
1#
#413
0#
b01100111 %
#414
1#
#415
0#
#416
1#
#417
0#
b01101000 %
#418
1#
#419
0#
#420
1#
#421
0#
b01101001 %
#422
1#
#423
0#
#424
1#
#425
0#
b01101010 %
#426
1#
#427
0#
#428
1#
#429
0#
b01101011 %
#430
1#
#431
0#
#432
1#
#433
0#
b01101100 %
#434
1#
#435
0#
#436
1#
#437
0#
b01101101 %
#438
1#
#439
0#
#440
1#
#441
0#
b01101110 %
#442
1#
#443
0#
#444
1#
#445
0#
b01101111 %
#446
1#
#447
0#
#448
1#
#449
0#
b01110000 %
#450
1#
#451
0#
#452
1#
#453
0#
b01110001 %
#454
1#
#455
0#
#456
1#
#457
0#
b01110010 %
#458
1#
#459
0#
#460
1#
#461
0#
b01110011 %
#462
1#
#463
0#
#464
1#
#465
0#
b01110100 %
#466
1#
#467
0#
#468
1#
#469
0#
b01110101 %
#470
1#
#471
0#
#472
1#
#473
0#
b01110110 %
#474
1#
#475
0#
#476
1#
#477
0#
b01110111 %
#478
1#
#479
0#
#480
1#
#481
0#
b01111000 %
#482
1#
#483
0#
#484
1#
#485
0#
b01111001 %
#486
1#
#487
0#
#488
1#
#489
0#
b01111010 %
#490
1#
#491
0#
#492
1#
#493
0#
b01111011 %
#494
1#
#495
0#
#496
1#
#497
0#
b01111100 %
#498
1#
#499
0#
#500
1#
#501
0#
b01111101 %
#502
1#
#503
0#
#504
1#
#505
0#
b01111110 %
#506
1#
#507
0#
#508
1#
#509
0#
b01111111 %
#510
1#
#511
0#
#512
1#
#513
0#
b10000000 %
#514
1#
#515
0#
#516
1#
#517
0#
b10000001 %
#518
1#
#519
0#
#520
1#
#521
0#
b10000010 %
#522
1#
#523
0#
#524
1#
#525
0#
b10000011 %
#526
1#
#527
0#
#528
1#
#529
0#
b10000100 %
#530
1#
#531
0#
#532
1#
#533
0#
b10000101 %
#534
1#
#535
0#
#536
1#
#537
0#
b10000110 %
#538
1#
#539
0#
#540
1#
#541
0#
b10000111 %
#542
1#
#543
0#
#544
1#
#545
0#
b10001000 %
#546
1#
#547
0#
#548
1#
#549
0#
b10001001 %
#550
1#
#551
0#
#552
1#
#553
0#
b10001010 %
#554
1#
#555
0#
#556
1#
#557
0#
b10001011 %
#558
1#
#559
0#
#560
1#
#561
0#
b10001100 %
#562
1#
#563
0#
#564
1#
#565
0#
b10001101 %
#566
1#
#567
0#
#568
1#
#569
0#
b10001110 %
#570
1#
#571
0#
#572
1#
#573
0#
b10001111 %
#574
1#
#575
0#
#576
1#
#577
0#
b10010000 %
#578
1#
#579
0#
#580
1#
#581
0#
b10010001 %
#582
1#
#583
0#
#584
1#
#585
0#
b10010010 %
#586
1#
#587
0#
#588
1#
#589
0#
b10010011 %
#590
1#
#591
0#
#592
1#
#593
0#
b10010100 %
#594
1#
#595
0#
#596
1#
#597
0#
b10010101 %
#598
1#
#599
0#
#600
1#
#601
0#
b10010110 %
#602
1#
#603
0#
#604
1#
#605
0#
b10010111 %
#606
1#
#607
0#
#608
1#
#609
0#
b10011000 %
#610
1#
#611
0#
#612
1#
#613
0#
b10011001 %
#614
1#
#615
0#
#616
1#
#617
0#
b10011010 %
#618
1#
#619
0#
#620
1#
#621
0#
b10011011 %
#622
1#
#623
0#
#624
1#
#625
0#
b10011100 %
#626
1#
#627
0#
#628
1#
#629
0#
b10011101 %
#630
1#
#631
0#
#632
1#
#633
0#
b10011110 %
#634
1#
#635
0#
#636
1#
#637
0#
b10011111 %
#638
1#
#639
0#
#640
1#
#641
0#
b10100000 %
#642
1#
#643
0#
#644
1#
#645
0#
b10100001 %
#646
1#
#647
0#
#648
1#
#649
0#
b10100010 %
#650
1#
#651
0#
#652
1#
#653
0#
b10100011 %
#654
1#
#655
0#
#656
1#
#657
0#
b10100100 %
#658
1#
#659
0#
#660
1#
#661
0#
b10100101 %
#662
1#
#663
0#
#664
1#
#665
0#
b10100110 %
#666
1#
#667
0#
#668
1#
#669
0#
b10100111 %
#670
1#
#671
0#
#672
1#
#673
0#
b10101000 %
#674
1#
#675
0#
#676
1#
#677
0#
b10101001 %
#678
1#
#679
0#
#680
1#
#681
0#
b10101010 %
#682
1#
#683
0#
#684
1#
#685
0#
b10101011 %
#686
1#
#687
0#
#688
1#
#689
0#
b10101100 %
#690
1#
#691
0#
#692
1#
#693
0#
b10101101 %
#694
1#
#695
0#
#696
1#
#697
0#
b10101110 %
#698
1#
#699
0#
#700
1#
#701
0#
b10101111 %
#702
1#
#703
0#
#704
1#
#705
0#
b10110000 %
#706
1#
#707
0#
#708
1#
#709
0#
b10110001 %
#710
1#
#711
0#
#712
1#
#713
0#
b10110010 %
#714
1#
#715
0#
#716
1#
#717
0#
b10110011 %
#718
1#
#719
0#
#720
1#
#721
0#
b10110100 %
#722
1#
#723
0#
#724
1#
#725
0#
b10110101 %
#726
1#
#727
0#
#728
1#
#729
0#
b10110110 %
#730
1#
#731
0#
#732
1#
#733
0#
b10110111 %
#734
1#
#735
0#
#736
1#
#737
0#
b10111000 %
#738
1#
#739
0#
#740
1#
#741
0#
b10111001 %
#742
1#
#743
0#
#744
1#
#745
0#
b10111010 %
#746
1#
#747
0#
#748
1#
#749
0#
b10111011 %
#750
1#
#751
0#
#752
1#
#753
0#
b10111100 %
#754
1#
#755
0#
#756
1#
#757
0#
b10111101 %
#758
1#
#759
0#
#760
1#
#761
0#
b10111110 %
#762
1#
#763
0#
#764
1#
#765
0#
b10111111 %
#766
1#
#767
0#
#768
1#
#769
0#
b11000000 %
#770
1#
#771
0#
#772
1#
#773
0#
b11000001 %
#774
1#
#775
0#
#776
1#
#777
0#
b11000010 %
#778
1#
#779
0#
#780
1#
#781
0#
b11000011 %
#782
1#
#783
0#
#784
1#
#785
0#
b11000100 %
#786
1#
#787
0#
#788
1#
#789
0#
b11000101 %
#790
1#
#791
0#
#792
1#
#793
0#
b11000110 %
#794
1#
#795
0#
#796
1#
#797
0#
b11000111 %
#798
1#
#799
0#
#800
1#
#801
0#
b11001000 %
#802
1#
#803
0#
#804
1#
#805
0#
b11001001 %
#806
1#
#807
0#
#808
1#
#809
0#
b11001010 %
#810
1#
#811
0#
#812
1#
#813
0#
b11001011 %
#814
1#
#815
0#
#816
1#
#817
0#
b11001100 %
#818
1#
#819
0#
#820
1#
#821
0#
b11001101 %
#822
1#
#823
0#
#824
1#
#825
0#
b11001110 %
#826
1#
#827
0#
#828
1#
#829
0#
b11001111 %
#830
1#
#831
0#
#832
1#
#833
0#
b11010000 %
#834
1#
#835
0#
#836
1#
#837
0#
b11010001 %
#838
1#
#839
0#
#840
1#
#841
0#
b11010010 %
#842
1#
#843
0#
#844
1#
#845
0#
b11010011 %
#846
1#
#847
0#
#848
1#
#849
0#
b11010100 %
#850
1#
#851
0#
#852
1#
#853
0#
b11010101 %
#854
1#
#855
0#
#856
1#
#857
0#
b11010110 %
#858
1#
#859
0#
#860
1#
#861
0#
b11010111 %
#862
1#
#863
0#
#864
1#
#865
0#
b11011000 %
#866
1#
#867
0#
#868
1#
#869
0#
b11011001 %
#870
1#
#871
0#
#872
1#
#873
0#
b11011010 %
#874
1#
#875
0#
#876
1#
#877
0#
b11011011 %
#878
1#
#879
0#
#880
1#
#881
0#
b11011100 %
#882
1#
#883
0#
#884
1#
#885
0#
b11011101 %
#886
1#
#887
0#
#888
1#
#889
0#
b11011110 %
#890
1#
#891
0#
#892
1#
#893
0#
b11011111 %
#894
1#
#895
0#
#896
1#
#897
0#
b11100000 %
#898
1#
#899
0#
#900
1#
#901
0#
b11100001 %
#902
1#
#903
0#
#904
1#
#905
0#
b11100010 %
#906
1#
#907
0#
#908
1#
#909
0#
b11100011 %
#910
1#
#911
0#
#912
1#
#913
0#
b11100100 %
#914
1#
#915
0#
#916
1#
#917
0#
b11100101 %
#918
1#
#919
0#
#920
1#
#921
0#
b11100110 %
#922
1#
#923
0#
#924
1#
#925
0#
b11100111 %
#926
1#
#927
0#
#928
1#
#929
0#
b11101000 %
#930
1#
#931
0#
#932
1#
#933
0#
b11101001 %
#934
1#
#935
0#
#936
1#
#937
0#
b11101010 %
#938
1#
#939
0#
#940
1#
#941
0#
b11101011 %
#942
1#
#943
0#
#944
1#
#945
0#
b11101100 %
#946
1#
#947
0#
#948
1#
#949
0#
b11101101 %
#950
1#
#951
0#
#952
1#
#953
0#
b11101110 %
#954
1#
#955
0#
#956
1#
#957
0#
b11101111 %
#958
1#
#959
0#
#960
1#
#961
0#
b11110000 %
#962
1#
#963
0#
#964
1#
#965
0#
b11110001 %
#966
1#
#967
0#
#968
1#
#969
0#
b11110010 %
#970
1#
#971
0#
#972
1#
#973
0#
b11110011 %
#974
1#
#975
0#
#976
1#
#977
0#
b11110100 %
#978
1#
#979
0#
#980
1#
#981
0#
b11110101 %
#982
1#
#983
0#
#984
1#
#985
0#
b11110110 %
#986
1#
#987
0#
#988
1#
#989
0#
b11110111 %
#990
1#
#991
0#
#992
1#
#993
0#
b11111000 %
#994
1#
#995
0#
#996
1#
#997
0#
b11111001 %
#998
1#
#999
0#
#1000
1#
#1001
0#
b11111010 %
#1002
1#
#1003
0#
#1004
1#
#1005
0#
b11111011 %
#1006
1#
#1007
0#
#1008
1#
#1009
0#
b11111100 %
#1010
1#
#1011
0#
#1012
1#
#1013
0#
b11111101 %
#1014
1#
#1015
0#
#1016
1#
#1017
0#
b11111110 %
#1018
1#
#1019
0#
#1020
1#
#1021
0#
b11111111 %
#1022
1#
#1023
0#
#1024
1#
#1025
0#
1$
b00000000 %
#1026
1#
#1027
0#
#1028
1#
#1029
0#
b00000001 %
#1030
1#
#1031
0#
#1032
1#
#1033
0#
b00000010 %
#1034
1#
#1035
0#
#1036
1#
#1037
0#
b00000011 %
#1038
1#
#1039
0#
#1040
1#
#1041
0#
b00000100 %
#1042
1#
#1043
0#
#1044
1#
#1045
0#
b00000101 %
#1046
1#
#1047
0#
#1048
1#
#1049
0#
b00000110 %
#1050
1#
#1051
0#
#1052
1#
#1053
0#
b00000111 %
#1054
1#
#1055
0#
#1056
1#
#1057
0#
b00001000 %
#1058
1#
#1059
0#
#1060
1#
#1061
0#
b00001001 %
#1062
1#
#1063
0#
#1064
1#
#1065
0#
b00001010 %
#1066
1#
#1067
0#
#1068
1#
#1069
0#
b00001011 %
#1070
1#
#1071
0#
#1072
1#
#1073
0#
b00001100 %
#1074
1#
#1075
0#
#1076
1#
#1077
0#
b00001101 %
#1078
1#
#1079
0#
#1080
1#
#1081
0#
b00001110 %
#1082
1#
#1083
0#
#1084
1#
#1085
0#
b00001111 %
#1086
1#
#1087
0#
#1088
1#
#1089
0#
b00010000 %
#1090
1#
#1091
0#
#1092
1#
#1093
0#
b00010001 %
#1094
1#
#1095
0#
#1096
1#
#1097
0#
b00010010 %
#1098
1#
#1099
0#
#1100
1#
#1101
0#
b00010011 %
#1102
1#
#1103
0#
#1104
1#
#1105
0#
b00010100 %
#1106
1#
#1107
0#
#1108
1#
#1109
0#
b00010101 %
#1110
1#
#1111
0#
#1112
1#
#1113
0#
b00010110 %
#1114
1#
#1115
0#
#1116
1#
#1117
0#
b00010111 %
#1118
1#
#1119
0#
#1120
1#
#1121
0#
b00011000 %
#1122
1#
#1123
0#
#1124
1#
#1125
0#
b00011001 %
#1126
1#
#1127
0#
#1128
1#
#1129
0#
b00011010 %
#1130
1#
#1131
0#
#1132
1#
#1133
0#
b00011011 %
#1134
1#
#1135
0#
#1136
1#
#1137
0#
b00011100 %
#1138
1#
#1139
0#
#1140
1#
#1141
0#
b00011101 %
#1142
1#
#1143
0#
#1144
1#
#1145
0#
b00011110 %
#1146
1#
#1147
0#
#1148
1#
#1149
0#
b00011111 %
#1150
1#
#1151
0#
#1152
1#
#1153
0#
b00100000 %
#1154
1#
#1155
0#
#1156
1#
#1157
0#
b00100001 %
#1158
1#
#1159
0#
#1160
1#
#1161
0#
b00100010 %
#1162
1#
#1163
0#
#1164
1#
#1165
0#
b00100011 %
#1166
1#
#1167
0#
#1168
1#
#1169
0#
b00100100 %
#1170
1#
#1171
0#
#1172
1#
#1173
0#
b00100101 %
#1174
1#
#1175
0#
#1176
1#
#1177
0#
b00100110 %
#1178
1#
#1179
0#
#1180
1#
#1181
0#
b00100111 %
#1182
1#
#1183
0#
#1184
1#
#1185
0#
b00101000 %
#1186
1#
#1187
0#
#1188
1#
#1189
0#
b00101001 %
#1190
1#
#1191
0#
#1192
1#
#1193
0#
b00101010 %
#1194
1#
#1195
0#
#1196
1#
#1197
0#
b00101011 %
#1198
1#
#1199
0#
#1200
1#
#1201
0#
b00101100 %
#1202
1#
#1203
0#
#1204
1#
#1205
0#
b00101101 %
#1206
1#
#1207
0#
#1208
1#
#1209
0#
b00101110 %
#1210
1#
#1211
0#
#1212
1#
#1213
0#
b00101111 %
#1214
1#
#1215
0#
#1216
1#
#1217
0#
b00110000 %
#1218
1#
#1219
0#
#1220
1#
#1221
0#
b00110001 %
#1222
1#
#1223
0#
#1224
1#
#1225
0#
b00110010 %
#1226
1#
#1227
0#
#1228
1#
#1229
0#
b00110011 %
#1230
1#
#1231
0#
#1232
1#
#1233
0#
b00110100 %
#1234
1#
#1235
0#
#1236
1#
#1237
0#
b00110101 %
#1238
1#
#1239
0#
#1240
1#
#1241
0#
b00110110 %
#1242
1#
#1243
0#
#1244
1#
#1245
0#
b00110111 %
#1246
1#
#1247
0#
#1248
1#
#1249
0#
b00111000 %
#1250
1#
#1251
0#
#1252
1#
#1253
0#
b00111001 %
#1254
1#
#1255
0#
#1256
1#
#1257
0#
b00111010 %
#1258
1#
#1259
0#
#1260
1#
#1261
0#
b00111011 %
#1262
1#
#1263
0#
#1264
1#
#1265
0#
b00111100 %
#1266
1#
#1267
0#
#1268
1#
#1269
0#
b00111101 %
#1270
1#
#1271
0#
#1272
1#
#1273
0#
b00111110 %
#1274
1#
#1275
0#
#1276
1#
#1277
0#
b00111111 %
#1278
1#
#1279
0#
#1280
1#
#1281
0#
b01000000 %
#1282
1#
#1283
0#
#1284
1#
#1285
0#
b01000001 %
#1286
1#
#1287
0#
#1288
1#
#1289
0#
b01000010 %
#1290
1#
#1291
0#
#1292
1#
#1293
0#
b01000011 %
#1294
1#
#1295
0#
#1296
1#
#1297
0#
b01000100 %
#1298
1#
#1299
0#
#1300
1#
#1301
0#
b01000101 %
#1302
1#
#1303
0#
#1304
1#
#1305
0#
b01000110 %
#1306
1#
#1307
0#
#1308
1#
#1309
0#
b01000111 %
#1310
1#
#1311
0#
#1312
1#
#1313
0#
b01001000 %
#1314
1#
#1315
0#
#1316
1#
#1317
0#
b01001001 %
#1318
1#
#1319
0#
#1320
1#
#1321
0#
b01001010 %
#1322
1#
#1323
0#
#1324
1#
#1325
0#
b01001011 %
#1326
1#
#1327
0#
#1328
1#
#1329
0#
b01001100 %
#1330
1#
#1331
0#
#1332
1#
#1333
0#
b01001101 %
#1334
1#
#1335
0#
#1336
1#
#1337
0#
b01001110 %
#1338
1#
#1339
0#
#1340
1#
#1341
0#
b01001111 %
#1342
1#
#1343
0#
#1344
1#
#1345
0#
b01010000 %
#1346
1#
#1347
0#
#1348
1#
#1349
0#
b01010001 %
#1350
1#
#1351
0#
#1352
1#
#1353
0#
b01010010 %
#1354
1#
#1355
0#
#1356
1#
#1357
0#
b01010011 %
#1358
1#
#1359
0#
#1360
1#
#1361
0#
b01010100 %
#1362
1#
#1363
0#
#1364
1#
#1365
0#
b01010101 %
#1366
1#
#1367
0#
#1368
1#
#1369
0#
b01010110 %
#1370
1#
#1371
0#
#1372
1#
#1373
0#
b01010111 %
#1374
1#
#1375
0#
#1376
1#
#1377
0#
b01011000 %
#1378
1#
#1379
0#
#1380
1#
#1381
0#
b01011001 %
#1382
1#
#1383
0#
#1384
1#
#1385
0#
b01011010 %
#1386
1#
#1387
0#
#1388
1#
#1389
0#
b01011011 %
#1390
1#
#1391
0#
#1392
1#
#1393
0#
b01011100 %
#1394
1#
#1395
0#
#1396
1#
#1397
0#
b01011101 %
#1398
1#
#1399
0#
#1400
1#
#1401
0#
b01011110 %
#1402
1#
#1403
0#
#1404
1#
#1405
0#
b01011111 %
#1406
1#
#1407
0#
#1408
1#
#1409
0#
b01100000 %
#1410
1#
#1411
0#
#1412
1#
#1413
0#
b01100001 %
#1414
1#
#1415
0#
#1416
1#
#1417
0#
b01100010 %
#1418
1#
#1419
0#
#1420
1#
#1421
0#
b01100011 %
#1422
1#
#1423
0#
#1424
1#
#1425
0#
b01100100 %
#1426
1#
#1427
0#
#1428
1#
#1429
0#
b01100101 %
#1430
1#
#1431
0#
#1432
1#
#1433
0#
b01100110 %
#1434
1#
#1435
0#
#1436
1#
#1437
0#
b01100111 %
#1438
1#
#1439
0#
#1440
1#
#1441
0#
b01101000 %
#1442
1#
#1443
0#
#1444
1#
#1445
0#
b01101001 %
#1446
1#
#1447
0#
#1448
1#
#1449
0#
b01101010 %
#1450
1#
#1451
0#
#1452
1#
#1453
0#
b01101011 %
#1454
1#
#1455
0#
#1456
1#
#1457
0#
b01101100 %
#1458
1#
#1459
0#
#1460
1#
#1461
0#
b01101101 %
#1462
1#
#1463
0#
#1464
1#
#1465
0#
b01101110 %
#1466
1#
#1467
0#
#1468
1#
#1469
0#
b01101111 %
#1470
1#
#1471
0#
#1472
1#
#1473
0#
b01110000 %
#1474
1#
#1475
0#
#1476
1#
#1477
0#
b01110001 %
#1478
1#
#1479
0#
#1480
1#
#1481
0#
b01110010 %
#1482
1#
#1483
0#
#1484
1#
#1485
0#
b01110011 %
#1486
1#
#1487
0#
#1488
1#
#1489
0#
b01110100 %
#1490
1#
#1491
0#
#1492
1#
#1493
0#
b01110101 %
#1494
1#
#1495
0#
#1496
1#
#1497
0#
b01110110 %
#1498
1#
#1499
0#
#1500
1#
#1501
0#
b01110111 %
#1502
1#
#1503
0#
#1504
1#
#1505
0#
b01111000 %
#1506
1#
#1507
0#
#1508
1#
#1509
0#
b01111001 %
#1510
1#
#1511
0#
#1512
1#
#1513
0#
b01111010 %
#1514
1#
#1515
0#
#1516
1#
#1517
0#
b01111011 %
#1518
1#
#1519
0#
#1520
1#
#1521
0#
b01111100 %
#1522
1#
#1523
0#
#1524
1#
#1525
0#
b01111101 %
#1526
1#
#1527
0#
#1528
1#
#1529
0#
b01111110 %
#1530
1#
#1531
0#
#1532
1#
#1533
0#
b01111111 %
#1534
1#
#1535
0#
#1536
1#
#1537
0#
b10000000 %
#1538
1#
#1539
0#
#1540
1#
#1541
0#
b10000001 %
#1542
1#
#1543
0#
#1544
1#
#1545
0#
b10000010 %
#1546
1#
#1547
0#
#1548
1#
#1549
0#
b10000011 %
#1550
1#
#1551
0#
#1552
1#
#1553
0#
b10000100 %
#1554
1#
#1555
0#
#1556
1#
#1557
0#
b10000101 %
#1558
1#
#1559
0#
#1560
1#
#1561
0#
b10000110 %
#1562
1#
#1563
0#
#1564
1#
#1565
0#
b10000111 %
#1566
1#
#1567
0#
#1568
1#
#1569
0#
b10001000 %
#1570
1#
#1571
0#
#1572
1#
#1573
0#
b10001001 %
#1574
1#
#1575
0#
#1576
1#
#1577
0#
b10001010 %
#1578
1#
#1579
0#
#1580
1#
#1581
0#
b10001011 %
#1582
1#
#1583
0#
#1584
1#
#1585
0#
b10001100 %
#1586
1#
#1587
0#
#1588
1#
#1589
0#
b10001101 %
#1590
1#
#1591
0#
#1592
1#
#1593
0#
b10001110 %
#1594
1#
#1595
0#
#1596
1#
#1597
0#
b10001111 %
#1598
1#
#1599
0#
#1600
1#
#1601
0#
b10010000 %
#1602
1#
#1603
0#
#1604
1#
#1605
0#
b10010001 %
#1606
1#
#1607
0#
#1608
1#
#1609
0#
b10010010 %
#1610
1#
#1611
0#
#1612
1#
#1613
0#
b10010011 %
#1614
1#
#1615
0#
#1616
1#
#1617
0#
b10010100 %
#1618
1#
#1619
0#
#1620
1#
#1621
0#
b10010101 %
#1622
1#
#1623
0#
#1624
1#
#1625
0#
b10010110 %
#1626
1#
#1627
0#
#1628
1#
#1629
0#
b10010111 %
#1630
1#
#1631
0#
#1632
1#
#1633
0#
b10011000 %
#1634
1#
#1635
0#
#1636
1#
#1637
0#
b10011001 %
#1638
1#
#1639
0#
#1640
1#
#1641
0#
b10011010 %
#1642
1#
#1643
0#
#1644
1#
#1645
0#
b10011011 %
#1646
1#
#1647
0#
#1648
1#
#1649
0#
b10011100 %
#1650
1#
#1651
0#
#1652
1#
#1653
0#
b10011101 %
#1654
1#
#1655
0#
#1656
1#
#1657
0#
b10011110 %
#1658
1#
#1659
0#
#1660
1#
#1661
0#
b10011111 %
#1662
1#
#1663
0#
#1664
1#
#1665
0#
b10100000 %
#1666
1#
#1667
0#
#1668
1#
#1669
0#
b10100001 %
#1670
1#
#1671
0#
#1672
1#
#1673
0#
b10100010 %
#1674
1#
#1675
0#
#1676
1#
#1677
0#
b10100011 %
#1678
1#
#1679
0#
#1680
1#
#1681
0#
b10100100 %
#1682
1#
#1683
0#
#1684
1#
#1685
0#
b10100101 %
#1686
1#
#1687
0#
#1688
1#
#1689
0#
b10100110 %
#1690
1#
#1691
0#
#1692
1#
#1693
0#
b10100111 %
#1694
1#
#1695
0#
#1696
1#
#1697
0#
b10101000 %
#1698
1#
#1699
0#
#1700
1#
#1701
0#
b10101001 %
#1702
1#
#1703
0#
#1704
1#
#1705
0#
b10101010 %
#1706
1#
#1707
0#
#1708
1#
#1709
0#
b10101011 %
#1710
1#
#1711
0#
#1712
1#
#1713
0#
b10101100 %
#1714
1#
#1715
0#
#1716
1#
#1717
0#
b10101101 %
#1718
1#
#1719
0#
#1720
1#
#1721
0#
b10101110 %
#1722
1#
#1723
0#
#1724
1#
#1725
0#
b10101111 %
#1726
1#
#1727
0#
#1728
1#
#1729
0#
b10110000 %
#1730
1#
#1731
0#
#1732
1#
#1733
0#
b10110001 %
#1734
1#
#1735
0#
#1736
1#
#1737
0#
b10110010 %
#1738
1#
#1739
0#
#1740
1#
#1741
0#
b10110011 %
#1742
1#
#1743
0#
#1744
1#
#1745
0#
b10110100 %
#1746
1#
#1747
0#
#1748
1#
#1749
0#
b10110101 %
#1750
1#
#1751
0#
#1752
1#
#1753
0#
b10110110 %
#1754
1#
#1755
0#
#1756
1#
#1757
0#
b10110111 %
#1758
1#
#1759
0#
#1760
1#
#1761
0#
b10111000 %
#1762
1#
#1763
0#
#1764
1#
#1765
0#
b10111001 %
#1766
1#
#1767
0#
