DigitalCircuitsExperiments/DCE07/ps2/ps2_keyboard/ps2_keyboard_sim/ps2_keyboard_sim_fn/test_1/ps2_keyboard_sim_fn.v
module ps2_keyboard_sim_fn(clk,clrn,ps2_clk,ps2_data,data,
                    ready,nextdata_n,overflow);
    input clk,clrn,ps2_clk,ps2_data;
    input nextdata_n;
    output [7:0] data;
    output reg ready;
    output reg overflow;     // fifo overflow
    // internal signal, for test
    reg [9:0] buffer;        // ps2_data bits
    reg [7:0] fifo[7:0];     // data fifo
    reg [2:0] w_ptr,r_ptr;   // fifo write and read pointers
    reg [3:0] count;  // count ps2_data bits
    // detect falling edge of ps2_clk
    reg [2:0] ps2_clk_sync;

    always @(posedge clk) begin
        ps2_clk_sync <=  {ps2_clk_sync[1:0],ps2_clk};
    end

    wire sampling = ps2_clk_sync[2] & ~ps2_clk_sync[1];

    always @(posedge clk) begin
        if (clrn == 0) begin // reset
            count <= 0; w_ptr <= 0; r_ptr <= 0; overflow <= 0; ready<= 0;
        end
        else begin
            if ( ready ) begin // read to output next data
                if(nextdata_n == 1'b0) //read next data
                begin
                    r_ptr <= r_ptr + 3'b1;
                    if(w_ptr==(r_ptr+1'b1)) //empty
                        ready <= 1'b0;
                end
            end
            if (sampling) begin
              if (count == 4'd10) begin
                if ((buffer[0] == 0) &&  // start bit
                    (ps2_data)       &&  // stop bit
                    (^buffer[9:1])) begin      // odd  parity
                    fifo[w_ptr] <= buffer[8:1];  // kbd scan code
                    w_ptr <= w_ptr+3'b1;
                    ready <= 1'b1;
                    overflow <= overflow | (r_ptr == (w_ptr + 3'b1));
                end
                count <= 0;     // for next
              end else begin
                buffer[count] <= ps2_data;  // store ps2_data
                count <= count + 3'b1;
              end
            end
        end
    end
    assign data = fifo[r_ptr]; //always set output data

endmodule

DigitalCircuitsExperiments/DCE07/ps2/ps2_keyboard/ps2_keyboard_sim/ps2_keyboard_sim_fn/same_clock/obj_dir/dump.vcd
$version Generated by VerilatedVcd $end
$date Thu Jan 26 18:46:06 2023 $end
$timescale 1s $end

 $scope module TOP $end
  $var wire  1 1 clk $end
  $var wire  1 2 clrn $end
  $var wire  8 6 data [7:0] $end
  $var wire  1 5 nextdata_n $end
  $var wire  1 8 overflow $end
  $var wire  1 3 ps2_clk $end
  $var wire  1 4 ps2_data $end
  $var wire  1 7 ready $end
  $scope module ps2_keyboard_sim_fn $end
   $var wire 10 # buffer [9:0] $end
   $var wire  1 1 clk $end
   $var wire  1 2 clrn $end
   $var wire  4 . count [3:0] $end
   $var wire  8 6 data [7:0] $end
   $var wire  8 $ fifo(0) [7:0] $end
   $var wire  8 % fifo(1) [7:0] $end
   $var wire  8 & fifo(2) [7:0] $end
   $var wire  8 ' fifo(3) [7:0] $end
   $var wire  8 ( fifo(4) [7:0] $end
   $var wire  8 ) fifo(5) [7:0] $end
   $var wire  8 * fifo(6) [7:0] $end
   $var wire  8 + fifo(7) [7:0] $end
   $var wire  1 5 nextdata_n $end
   $var wire  1 8 overflow $end
   $var wire  1 3 ps2_clk $end
   $var wire  3 / ps2_clk_sync [2:0] $end
   $var wire  1 4 ps2_data $end
   $var wire  3 - r_ptr [2:0] $end
   $var wire  1 7 ready $end
   $var wire  1 0 sampling $end
   $var wire  3 , w_ptr [2:0] $end
  $upscope $end
 $upscope $end
$enddefinitions $end


#1
b0000000000 #
b00000000 $
b00000000 %
b00000000 &
b00000000 '
b00000000 (
b00000000 )
b00000000 *
b00000000 +
b000 ,
b000 -
b0000 .
b000 /
00
01
12
13
04
15
b00000000 6
07
08
#2
b001 /
11
#3
01
03
#4
b010 /
11
#5
01
13
14
#6
b101 /
10
11
#7
01
03
#8
b0000000001 #
b0001 .
b010 /
00
11
#9
01
13
04
#10
b101 /
10
11
#11
01
03
#12
b0010 .
b010 /
00
11
#13
01
13
14
#14
b101 /
10
11
#15
01
03
#16
b0000000101 #
b0011 .
b010 /
00
11
#17
01
13
04
#18
b101 /
10
11
#19
01
03
#20
b0100 .
b010 /
00
11
#21
01
13
#22
b101 /
10
11
#23
01
03
#24
b0101 .
b010 /
00
11
#25
01
13
#26
b101 /
10
11
#27
01
03
#28
b0110 .
b010 /
00
11
#29
01
13
#30
b101 /
10
11
#31
01
03
#32
b0111 .
b010 /
00
11
#33
01
13
#34
b101 /
10
11
#35
01
03
#36
b1000 .
b010 /
00
11
#37
01
13
14
#38
b101 /
10
11
#39
01
03
#40
b0100000101 #
b1001 .
b010 /
00
11
#41
01
13
#42
b101 /
10
11
#43
01
03
#44
b1100000101 #
b1010 .
b010 /
00
11
#45
01
13
04
05
#46
b101 /
10
11
#47
01
03
#48
b0000 .
b010 /
00
11
#49
01
13
15
#50
b101 /
10
11
#51
01
03
#52
b1100000100 #
b0001 .
b010 /
00
11
#53
01
13
#54
b101 /
10
11
#55
01
03
#56
b0010 .
b010 /
00
11
#57
01
13
14
#58
b101 /
10
11
#59
01
03
#60
b0011 .
b010 /
00
11
#61
01
13
#62
b101 /
10
11
#63
01
03
#64
b1100001100 #
b0100 .
b010 /
00
11
#65
01
13
04
#66
b101 /
10
11
#67
01
03
#68
b0101 .
b010 /
00
11
#69
01
13
#70
b101 /
10
11
#71
01
03
#72
b0110 .
b010 /
00
11
#73
01
13
#74
b101 /
10
11
#75
01
03
#76
b0111 .
b010 /
00
11
#77
01
13
#78
b101 /
10
11
#79
01
03
#80
b1000 .
b010 /
00
11
#81
01
13
#82
b101 /
10
11
#83
01
03
#84
b1000001100 #
b1001 .
b010 /
00
11
#85
01
13
14
#86
b101 /
10
11
#87
01
03
#88
b1010 .
b010 /
00
11
#89
01
13
#90
b101 /
10
11
#91
01
03
05
#92
b00000110 $
b001 ,
b0000 .
b010 /
00
11
b00000110 6
17
#93
01
13
04
#94
b001 -
b101 /
10
11
b00000000 6
07
#95
01
03
#96
b0001 .
b010 /
00
11
#97
01
13
15
#98
b101 /
10
11
#99
01
#100
b0010 .
b011 /
00
11
#101
01
#102
b111 /
11
#103
01
#104
11
#105
01
03
#106
b110 /
11
#107
01
#108
b100 /
10
11
#109
01
#110
b1000001000 #
b0011 .
b000 /
00
11
#111
01
#112
11
#113
01
13
#114
b001 /
11
#115
01
#116
b011 /
11
#117
01
#118
b111 /
11
#119
01
#120
11
#121
01
03
#122
b110 /
11
#123
01
#124
b100 /
10
11
#125
01
#126
b1000000000 #
b0100 .
b000 /
00
11
#127
01
#128
11
#129
01
13
#130
b001 /
11
#131
01
#132
b011 /
11
#133
01
#134
b111 /
11
#135
01
#136
11
#137
01
03
#138
b110 /
11
#139
01
#140
b100 /
10
11
#141
01
#142
b0101 .
b000 /
00
11
#143
01
#144
11
#145
01
13
14
#146
b001 /
11
#147
01
#148
b011 /
11
#149
01
#150
b111 /
11
#151
01
#152
11
#153
01
03
#154
b110 /
11
#155
01
#156
b100 /
10
11
#157
01
#158
b1000100000 #
b0110 .
b000 /
00
11
#159
01
#160
11
#161
01
13
04
#162
b001 /
11
#163
01
#164
b011 /
11
#165
01
#166
b111 /
11
#167
01
#168
11
#169
01
03
#170
b110 /
11
#171
01
#172
b100 /
10
11
#173
01
#174
b0111 .
b000 /
00
11
#175
01
#176
11
#177
01
13
#178
b001 /
11
#179
01
#180
b011 /
11
#181
01
#182
b111 /
11
#183
01
#184
11
#185
01
03
#186
b110 /
11
#187
01
#188
b100 /
10
11
#189
01
#190
b1000 .
b000 /
00
11
#191
01
#192
11
#193
01
13
#194
b001 /
11
#195
01
#196
b011 /
11
#197
01
#198
b111 /
11
#199
01
#200
11
#201
01
03
#202
b110 /
11
#203
01
#204
b100 /
10
11
#205
01
#206
b1001 .
b000 /
00
11
#207
01
#208
11
#209
01
13
#210
b001 /
11
#211
01
#212
b011 /
11
#213
01
#214
b111 /
11
#215
01
#216
11
#217
01
03
#218
b110 /
11
#219
01
#220
b100 /
10
11
#221
01
#222
b0000100000 #
b1010 .
b000 /
00
11
#223
01
#224
11
#225
01
13
#226
b001 /
11
#227
01
#228
b011 /
11
#229
01
#230
b111 /
11
#231
01
#232
11
#233
01
03
#234
b110 /
11
#235
01
#236
b100 /
10
11
#237
01
#238
b0000 .
b000 /
00
11
#239
01
#240
11
#241
01
13
14
#242
b001 /
11
#243
01
#244
b011 /
11
#245
01
#246
b111 /
11
#247
01
#248
11
#249
01
03
#250
b110 /
11
#251
01
#252
b100 /
10
11
#253
01
#254
b0000100001 #
b0001 .
b000 /
00
11
#255
01
#256
11
#257
01
13
#258
b001 /
11
#259
01
#260
b011 /
11
#261
01
#262
b111 /
11
#263
01
#264
11
#265
01
03
#266
b110 /
11
#267
01
#268
b100 /
10
11
#269
01
#270
b0000100011 #
b0010 .
b000 /
00
11
#271
01
05
#272
11
#273
01
13
04
15
#274
b001 /
11
#275
01
#276
b011 /
11
#277
01
#278
b111 /
11
#279
01
#280
11
#281
01
03
#282
b110 /
11
#283
01
#284
b100 /
10
11
#285
01
#286
b0011 .
b000 /
00
11
#287
01
#288
11
#289
01
13
#290
b001 /
11
#291
01
#292
b011 /
11
#293
01
#294
b111 /
11
#295
01
#296
11
#297
01
03
#298
b110 /
11
#299
01
#300
b100 /
10
11
#301
01
#302
b0100 .
b000 /
00
11
#303
01
#304
11
#305
01
13
#306
b001 /
11
#307
01
#308
b011 /
11
#309
01
#310
b111 /
11
#311
01
#312
11
#313
01
03
#314
b110 /
11
#315
01
#316
b100 /
10
11
#317
01
#318
b0101 .
b000 /
00
11
#319
01
#320
11
#321
01
13
14
#322
b001 /
11
#323
01
#324
b011 /
11
#325
01
#326
b111 /
11
#327
01
#328
11
#329
01
03
#330
b110 /
11
#331
01
#332
b100 /
10
11
#333
01
#334
b0110 .
b000 /
00
11
#335
01
#336
11
#337
01
13
#338
b001 /
11
#339
01
#340
b011 /
11
#341
01
#342
b111 /
11
#343
01
#344
11
#345
01
03
#346
b110 /
11
#347
01
#348
b100 /
10
11
#349
01
#350
b0001100011 #
b0111 .
b000 /
00
11
#351
01
#352
11
#353
01
13
04
#354
b001 /
11
#355
01
#356
b011 /
11
#357
01
#358
b111 /
11
#359
01
#360
11
#361
01
03
#362
b110 /
11
#363
01
#364
b100 /
10
11
#365
01
#366
b1000 .
b000 /
00
11
#367
01
#368
11
#369
01
13
#370
b001 /
11
#371
01
#372
b011 /
11
#373
01
#374
b111 /
11
#375
01
#376
11
#377
01
03
#378
b110 /
11
#379
01
#380
b100 /
10
11
#381
01
#382
b1001 .
b000 /
00
11
#383
01
#384
11
#385
01
13
#386
b001 /
11
#387
01
#388
b011 /
11
#389
01
#390
b111 /
11
#391
01
#392
11
#393
01
03
#394
b110 /
11
#395
01
#396
b100 /
10
11
#397
01
#398
b1010 .
b000 /
00
11
#399
01
#400
11
#401
01
13
#402
b001 /
11
#403
01
#404
b011 /
11
#405
01
#406
b111 /
11
#407
01
#408
11
#409
01
03
#410
b110 /
11
#411
01
#412
b100 /
10
11
#413
01
#414
b0000 .
b000 /
00
11
#415
01
#416
11
#417
01
13
14
#418
b001 /
11
#419
01
#420
b011 /
11
#421
01
#422
b111 /
11
#423
01
#424
11
#425
01
03
#426
b110 /
11
#427
01
#428
b100 /
10
11
#429
01
#430
b0001 .
b000 /
00
11
#431
01
#432
11
#433
01
13
#434
b001 /
11
#435
01
#436
b011 /
11
#437
01
#438
b111 /
11
#439
01
#440
11
#441
01
03
#442
b110 /
11
#443
01
#444
b100 /
10
11
#445
01
#446
b0010 .
b000 /
00
11
#447
01
05
#448
11
#449
01
13
04
15
#450
b001 /
11
#451
01
#452
b011 /
11
#453
01
#454
b111 /
11
#455
01
#456
11
#457
01
03
#458
b110 /
11
#459
01
#460
b100 /
10
11
#461
01
#462
b0011 .
b000 /
00
11
#463
01
#464
11
#465
01
13
14
#466
b001 /
11
#467
01
#468
b011 /
11
#469
01
#470
b111 /
11
#471
01
#472
11
#473
01
03
#474
b110 /
11
#475
01
#476
b100 /
10
11
#477
01
#478
b0001101011 #
b0100 .
b000 /
00
11
#479
01
#480
11
#481
01
13
#482
b001 /
11
#483
01
#484
b011 /
11
#485
01
#486
b111 /
11
#487
01
#488
11
#489
01
03
#490
b110 /
11
#491
01
#492
b100 /
10
11
#493
01
#494
b0001111011 #
b0101 .
b000 /
00
11
#495
01
#496
11
#497
01
13
04
#498
b001 /
11
#499
01
#500
b011 /
11
#501
01
#502
b111 /
11
#503
01
#504
11
#505
01
03
#506
b110 /
11
#507
01
#508
b100 /
10
11
#509
01
#510
b0001011011 #
b0110 .
b000 /
00
11
#511
01
#512
11
#513
01
13
#514
b001 /
11
#515
01
#516
b011 /
11
#517
01
#518
b111 /
11
#519
01
#520
11
#521
01
03
#522
b110 /
11
#523
01
#524
b100 /
10
11
#525
01
#526
b0000011011 #
b0111 .
b000 /
00
11
#527
01
#528
11
#529
01
13
#530
b001 /
11
#531
01
#532
b011 /
11
#533
01
#534
b111 /
11
#535
01
#536
11
#537
01
03
#538
b110 /
11
#539
01
#540
b100 /
10
11
#541
01
#542
b1000 .
b000 /
00
11
#543
01
#544
11
#545
01
13
#546
b001 /
11
#547
01
#548
b011 /
11
#549
01
#550
b111 /
11
#551
01
#552
11
#553
01
03
#554
b110 /
11
#555
01
#556
b100 /
10
11
#557
01
#558
b1001 .
b000 /
00
11
#559
01
#560
11
#561
01
13
#562
b001 /
11
#563
01
#564
b011 /
11
#565
01
#566
b111 /
11
#567
01
#568
11
#569
01
03
#570
b110 /
11
#571
01
#572
b100 /
10
11
#573
01
#574
b1010 .
b000 /
00
11
#575
01
#576
11
#577
01
13
#578
b001 /
11
#579
01
#580
b011 /
11
#581
01
#582
b111 /
11
#583
01
#584
11
#585
01
03
#586
b110 /
11
#587
01
#588
b100 /
10
11
#589
01
#590
b0000 .
b000 /
00
11
#591
01
#592
11
#593
01
13
14
#594
b001 /
11
#595
01
#596
b011 /
11
#597
01
#598
b111 /
11
#599
01
#600
11
#601
01
03
#602
b110 /
11
#603
01
#604
b100 /
10
11
#605
01
#606
b0001 .
b000 /
00
11
#607
01
#608
11
#609
01
13
#610
b001 /
11
#611
01
#612
b011 /
11
#613
01
#614
b111 /
11
#615
01
#616
11
#617
01
03
#618
b110 /
11
#619
01
#620
b100 /
10
11
#621
01
#622
b0010 .
b000 /
00
11
#623
01
05
#624
11
#625
01
13
04
15
#626
b001 /
11
#627
01
#628
b011 /
11
#629
01
#630
b111 /
11
#631
01
#632
11
#633
01
03
#634
b110 /
11
#635
01
#636
b100 /
10
11
#637
01
#638
b0011 .
b000 /
00
11
#639
01
#640
11
#641
01
13
14
#642
b001 /
11
#643
01
#644
b011 /
11
#645
01
#646
b111 /
11
#647
01
#648
11
#649
01
03
#650
b110 /
11
#651
01
#652
b100 /
10
11
#653
01
#654
b0100 .
b000 /
00
11
#655
01
#656
11
#657
01
13
#658
b001 /
11
#659
01
#660
b011 /
11
#661
01
#662
b111 /
11
#663
01
#664
11
#665
01
03
#666
b110 /
11
#667
01
#668
b100 /
10
11
#669
01
#670
b0101 .
b000 /
00
11
#671
01
#672
11
#673
01
13
04
#674
b001 /
11
#675
01
#676
b011 /
11
#677
01
#678
b111 /
11
#679
01
#680
11
#681
01
03
#682
b110 /
11
#683
01
#684
b100 /
10
11
#685
01
#686
b0110 .
b000 /
00
11
#687
01
#688
11
#689
01
13
14
#690
b001 /
11
#691
01
#692
b011 /
11
#693
01
#694
b111 /
11
#695
01
#696
11
#697
01
03
#698
b110 /
11
#699
01
#700
b100 /
10
11
#701
01
#702
b0001011011 #
b0111 .
b000 /
00
11
#703
01
#704
11
#705
01
13
04
#706
b001 /
11
#707
01
#708
b011 /
11
#709
01
#710
b111 /
11
#711
01
#712
11
#713
01
03
#714
b110 /
11
#715
01
#716
b100 /
10
11
#717
01
#718
b1000 .
b000 /
00
11
#719
01
#720
11
#721
01
13
#722
b001 /
11
#723
01
#724
b011 /
11
#725
01
#726
b111 /
11
#727
01
#728
11
#729
01
03
#730
b110 /
11
#731
01
#732
b100 /
10
11
#733
01
#734
b1001 .
b000 /
00
11
#735
01
#736
11
#737
01
13
#738
b001 /
11
#739
01
#740
b011 /
11
#741
01
#742
b111 /
11
#743
01
#744
11
#745
01
03
#746
b110 /
11
#747
01
#748
b100 /
10
11
#749
01
#750
b1010 .
b000 /
00
11
#751
01
#752
11
#753
01
13
#754
b001 /
11
#755
01
#756
b011 /
11
#757
01
#758
b111 /
11
#759
01
#760
11
#761
01
03
#762
b110 /
11
#763
01
#764
b100 /
10
11
#765
01
#766
b0000 .
b000 /
00
11
#767
01
#768
11
#769
01
13
14
#770
b001 /
11
#771
01
#772
b011 /
11
#773
01
#774
b111 /
11
#775
01
#776
11
#777
01
03
#778
b110 /
11
#779
01
#780
b100 /
10
11
#781
01
#782
b0001 .
b000 /
00
11
#783
01
#784
11
#785
01
13
#786
b001 /
11
#787
01
#788
b011 /
11
#789
01
#790
b111 /
11
#791
01
#792
11
#793
01
03
#794
b110 /
11
#795
01
#796
b100 /
10
11
#797
01
#798
b0010 .
b000 /
00
11
#799
01
05
#800
11
#801
01
13
04
15
#802
b001 /
11
#803
01
#804
b011 /
11
#805
01
#806
b111 /
11
#807
01
#808
11
#809
01
03
#810
b110 /
11
#811
01
#812
b100 /
10
11
#813
01
#814
b0011 .
b000 /
00
11
#815
01
#816
11
#817
01
13
14
#818
b001 /
11
#819
01
#820
b011 /
11
#821
01
#822
b111 /
11
#823
01
#824
11
#825
01
03
#826
b110 /
11
#827
01
#828
b100 /
10
11
#829
01
#830
b0100 .
b000 /
00
11
#831
01
#832
11
#833
01
13
#834
b001 /
11
#835
01
#836
b011 /
11
#837
01
#838
b111 /
11
#839
01
#840
11
#841
01
03
#842
b110 /
11
#843
01
#844
b100 /
10
11
#845
01
#846
b0101 .
b000 /
00
11
#847
01
#848
11
#849
01
13
04
#850
b001 /
11
#851
01
#852
b011 /
11
#853
01
#854
b111 /
11
#855
01
#856
11
#857
01
03
#858
b110 /
11
#859
01
#860
b100 /
10
11
#861
01
#862
b0110 .
b000 /
00
11
#863
01
#864
11
#865
01
13
#866
b001 /
11
#867
01
#868
b011 /
11
#869
01
#870
b111 /
11
#871
01
#872
11
#873
01
03
#874
b110 /
11
#875
01
#876
b100 /
10
11
#877
01
#878
b0000011011 #
b0111 .
b000 /
00
11
#879
01
#880
11
#881
01
13
#882
b001 /
11
#883
01
#884
b011 /
11
#885
01
#886
b111 /
11
#887
01
#888
11
#889
01
03
#890
b110 /
11
#891
01
#892
b100 /
10
11
#893
01
#894
b1000 .
b000 /
00
11
#895
01
#896
11
#897
01
13
#898
b001 /
11
#899
01
#900
b011 /
11
#901
01
#902
b111 /
11
#903
01
#904
11
#905
01
03
#906
b110 /
11
#907
01
#908
b100 /
10
11
#909
01
#910
b1001 .
b000 /
00
11
#911
01
#912
11
#913
01
13
#914
b001 /
11
#915
01
#916
b011 /
11
#917
01
#918
b111 /
11
#919
01
#920
11
#921
01
03
#922
b110 /
11
#923
01
#924
b100 /
10
11
#925
01
#926
b1010 .
b000 /
00
11
#927
01
#928
11
#929
01
13
14
#930
b001 /
11
#931
01
#932
b011 /
11
#933
01
#934
b111 /
11
#935
01
#936
11
#937
01
03
#938
b110 /
11
#939
01
#940
b100 /
10
11
#941
01
#942
b0000 .
b000 /
00
11
#943
01
#944
11
#945
01
13
#946
b001 /
11
#947
01
#948
b011 /
11
#949
01
#950
b111 /
11
#951
01
#952
11
#953
01
03
#954
b110 /
11
#955
01
#956
b100 /
10
11
#957
01
#958
b0001 .
b000 /
00
11
#959
01
#960
11
#961
01
13
#962
b001 /
11
#963
01
#964
b011 /
11
#965
01
#966
b111 /
11
#967
01
#968
11
#969
01
03
#970
b110 /
11
#971
01
#972
b100 /
10
11
#973
01
#974
b0010 .
b000 /
00
11
#975
01
05
#976
11
#977
01
13
04
15
#978
b001 /
11
#979
01
#980
b011 /
11
#981
01
#982
b111 /
11
#983
01
#984
11
#985
01
03
#986
b110 /
11
#987
01
#988
b100 /
10
11
#989
01
#990
b0011 .
b000 /
00
11
#991
01
#992
11
#993
01
13
#994
b001 /
11
#995
01
#996
b011 /
11
#997
01
#998
b111 /
11
#999
01
#1000
11
#1001
01
03
#1002
b110 /
11
#1003
01
#1004
b100 /
10
11
#1005
01
#1006
b0000010011 #
b0100 .
b000 /
00
11
#1007
01
#1008
11
#1009
01
13
14
#1010
b001 /
11
#1011
01
#1012
b011 /
11
#1013
01
#1014
b111 /
11
#1015
01
#1016
11
#1017
01
03
#1018
b110 /
11
#1019
01
#1020
b100 /
10
11
#1021
01
#1022
b0101 .
b000 /
00
11
#1023
01
#1024
11
#1025
01
13
04
#1026
b001 /
11
#1027
01
#1028
b011 /
11
#1029
01
#1030
b111 /
11
#1031
01
#1032
11
#1033
01
03
#1034
b110 /
11
#1035
01
#1036
b100 /
10
11
#1037
01
#1038
b0110 .
b000 /
00
11
#1039
01
#1040
11
#1041
01
13
14
#1042
b001 /
11
#1043
01
#1044
b011 /
11
#1045
01
#1046
b111 /
11
#1047
01
#1048
11
#1049
01
03
#1050
b110 /
11
#1051
01
#1052
b100 /
10
11
#1053
01
#1054
b0001010011 #
b0111 .
b000 /
00
11
#1055
01
#1056
11
#1057
01
13
04
#1058
b001 /
11
#1059
01
#1060
b011 /
11
#1061
01
#1062
b111 /
11
#1063
01
#1064
11
#1065
01
03
#1066
b110 /
11
#1067
01
#1068
b100 /
10
11
#1069
01
#1070
b1000 .
b000 /
00
11
#1071
01
#1072
11
#1073
01
13
#1074
b001 /
11
#1075
01
#1076
b011 /
11
#1077
01
#1078
b111 /
11
#1079
01
#1080
11
#1081
01
03
#1082
b110 /
11
#1083
01
#1084
b100 /
10
11
#1085
01
#1086
b1001 .
b000 /
00
11
#1087
01
#1088
11
#1089
01
13
#1090
b001 /
11
#1091
01
#1092
b011 /
11
#1093
01
#1094
b111 /
11
#1095
01
#1096
11
#1097
01
03
#1098
b110 /
11
#1099
01
#1100
b100 /
10
11
#1101
01
#1102
b1010 .
b000 /
00
11
#1103
01
#1104
11
#1105
01
13
#1106
b001 /
11
#1107
01
#1108
b011 /
11
#1109
01
#1110
b111 /
11
#1111
01
#1112
11
#1113
01
03
#1114
b110 /
11
#1115
01
#1116
b100 /
10
11
#1117
01
#1118
b0000 .
b000 /
00
11
#1119
01
#1120
11
#1121
01
13
14
#1122
b001 /
11
#1123
01
#1124
b011 /
11
#1125
01
#1126
b111 /
11
#1127
01
#1128
11
#1129
01
03
#1130
b110 /
11
#1131
01
#1132
b100 /
10
11
#1133
01
#1134
b0001 .
b000 /
00
11
#1135
01
#1136
11
#1137
01
13
#1138
b001 /
11
#1139
01
#1140
b011 /
11
#1141
01
#1142
b111 /
11
#1143
01
#1144
11
#1145
01
03
#1146
b110 /
11
#1147
01
#1148
b100 /
10
11
#1149
01
#1150
b0010 .
b000 /
00
11
#1151
01
05
#1152
11
#1153
01
13
04
15
#1154
b001 /
11
#1155
01
#1156
b011 /
11
#1157
01
#1158
b111 /
11
#1159
01
#1160
11
#1161
01
03
#1162
b110 /
11
#1163
01
#1164
b100 /
10
11
#1165
01
#1166
b0011 .
b000 /
00
11
#1167
01
#1168
11
#1169
01
13
14
#1170
b001 /
11
#1171
01
#1172
b011 /
11
#1173
01
#1174
b111 /
11
#1175
01
#1176
11
#1177
01
03
#1178
b110 /
11
#1179
01
#1180
b100 /
10
11
#1181
01
#1182
b0001011011 #
b0100 .
b000 /
00
11
#1183
01
#1184
11
#1185
01
13
04
#1186
b001 /
11
#1187
01
#1188
b011 /
11
#1189
01
#1190
b111 /
11
#1191
01
#1192
11
#1193
01
03
#1194
b110 /
11
#1195
01
#1196
b100 /
10
11
#1197
01
#1198
b0001001011 #
b0101 .
b000 /
00
11
#1199
01
#1200
11
#1201
01
13
#1202
b001 /
11
#1203
01
#1204
b011 /
11
#1205
01
#1206
b111 /
11
#1207
01
#1208
11
#1209
01
03
#1210
b110 /
11
#1211
01
#1212
b100 /
10
11
#1213
01
#1214
b0110 .
b000 /
00
11
#1215
01
#1216
11
#1217
01
13
#1218
b001 /
11
#1219
01
#1220
b011 /
11
#1221
01
#1222
b111 /
11
#1223
01
#1224
11
#1225
01
03
#1226
b110 /
11
#1227
01
#1228
b100 /
10
11
#1229
01
#1230
b0000001011 #
b0111 .
b000 /
00
11
#1231
01
#1232
11
#1233
01
13
#1234
b001 /
11
#1235
01
#1236
b011 /
11
#1237
01
#1238
b111 /
11
#1239
01
#1240
11
#1241
01
03
#1242
b110 /
11
#1243
01
#1244
b100 /
10
11
#1245
01
#1246
b1000 .
b000 /
00
11
#1247
01
#1248
11
#1249
01
13
#1250
b001 /
11
#1251
01
#1252
b011 /
11
#1253
01
#1254
b111 /
11
#1255
01
#1256
11
#1257
01
03
#1258
b110 /
11
#1259
01
#1260
b100 /
10
11
#1261
01
#1262
b1001 .
b000 /
00
11
#1263
01
#1264
11
#1265
01
13
#1266
b001 /
11
#1267
01
#1268
b011 /
11
#1269
01
#1270
b111 /
11
#1271
01
#1272
11
#1273
01
03
#1274
b110 /
11
#1275
01
#1276
b100 /
10
11
#1277
01
#1278
b1010 .
b000 /
00
11
#1279
01
#1280
11
#1281
01
13
#1282
b001 /
11
#1283
01
#1284
b011 /
11
#1285
01
#1286
b111 /
11
#1287
01
#1288
11
#1289
01
03
#1290
b110 /
11
#1291
01
#1292
b100 /
10
11
#1293
01
#1294
b0000 .
b000 /
00
11
#1295
01
#1296
11
#1297
01
13
14
#1298
b001 /
11
#1299
01
#1300
b011 /
11
#1301
01
#1302
b111 /
11
#1303
01
#1304
11
#1305
01
03
#1306
b110 /
11
#1307
01
#1308
b100 /
10
11
#1309
01
#1310
b0001 .
b000 /
00
11
#1311
01
#1312
11
#1313
01
13
#1314
b001 /
11
#1315
01
#1316
b011 /
11
#1317
01
#1318
b111 /
11
#1319
01
#1320
11
#1321
01
03
#1322
b110 /
11
#1323
01
#1324
b100 /
10
11
#1325
01
#1326
b0010 .
b000 /
00
11
#1327
01
05
#1328
11
#1329
01
13
04
15
#1330
b001 /
11
#1331
01
#1332
b011 /
11
#1333
01
#1334
b111 /
11
#1335
01
#1336
11
#1337
01
03
#1338
b110 /
11
#1339
01
#1340
b100 /
10
11
#1341
01
#1342
b0011 .
b000 /
00
11
#1343
01
#1344
11
#1345
01
13
14
#1346
b001 /
11
#1347
01
#1348
b011 /
11
#1349
01
#1350
b111 /
11
#1351
01
#1352
11
#1353
01
03
#1354
b110 /
11
#1355
01
#1356
b100 /
10
11
#1357
01
#1358
b0100 .
b000 /
00
11
#1359
01
#1360
11
#1361
01
13
04
#1362
b001 /
11
#1363
01
#1364
b011 /
11
#1365
01
#1366
b111 /
11
#1367
01
#1368
11
#1369
01
03
#1370
b110 /
11
#1371
01
#1372
b100 /
10
11
#1373
01
#1374
b0101 .
b000 /
00
11
#1375
01
#1376
11
#1377
01
13
#1378
b001 /
11
#1379
01
#1380
b011 /
11
#1381
01
#1382
b111 /
11
#1383
01
#1384
11
#1385
01
03
#1386
b110 /
11
#1387
01
#1388
b100 /
10
11
#1389
01
#1390
b0110 .
b000 /
00
11
#1391
01
#1392
11
#1393
01
13
14
#1394
b001 /
11
#1395
01
#1396
b011 /
11
#1397
01
#1398
b111 /
11
#1399
01
#1400
11
#1401
01
03
#1402
b110 /
11
#1403
01
#1404
b100 /
10
11
#1405
01
#1406
b0001001011 #
b0111 .
b000 /
00
11
#1407
01
#1408
11
#1409
01
13
04
#1410
b001 /
11
#1411
01
#1412
b011 /
11
#1413
01
#1414
b111 /
11
#1415
01
#1416
11
#1417
01
03
#1418
b110 /
11
#1419
01
#1420
b100 /
10
11
#1421
01
#1422
b1000 .
b000 /
00
11
#1423
01
#1424
11
#1425
01
13
#1426
b001 /
11
#1427
01
#1428
b011 /
11
#1429
01
#1430
b111 /
11
#1431
01
#1432
11
#1433
01
03
#1434
b110 /
11
#1435
01
#1436
b100 /
10
11
#1437
01
#1438
b1001 .
b000 /
00
11
#1439
01
#1440
11
#1441
01
13
#1442
b001 /
11
#1443
01
#1444
b011 /
11
#1445
01
#1446
b111 /
11
#1447
01
#1448
11
#1449
01
03
#1450
b110 /
11
#1451
01
#1452
b100 /
10
11
#1453
01
#1454
b1010 .
b000 /
00
11
#1455
01
#1456
11
#1457
01
13
#1458
b001 /
11
#1459
01
#1460
b011 /
11
#1461
01
#1462
b111 /
11
#1463
01
#1464
11
#1465
01
03
#1466
b110 /
11
#1467
01
#1468
b100 /
10
11
#1469
01
#1470
b0000 .
b000 /
00
11
#1471
01
#1472
11
#1473
01
13
14
#1474
b001 /
11
#1475
01
#1476
b011 /
11
#1477
01
#1478
b111 /
11
#1479
01
#1480
11
#1481
01
03
#1482
b110 /
11
#1483
01
#1484
b100 /
10
11
#1485
01
#1486
b0001 .
b000 /
00
11
#1487
01
#1488
11
#1489
01
13
#1490
b001 /
11
#1491
01
#1492
b011 /
11
#1493
01
#1494
b111 /
11
#1495
01
#1496
11
#1497
01
03
#1498
b110 /
11
#1499
01
#1500
b100 /
10
11
#1501
01
#1502
b0010 .
b000 /
00
11
#1503
01
05
#1504
11
#1505
01
13
04
15
#1506
b001 /
11
#1507
01
#1508
b011 /
11
#1509
01
#1510
b111 /
11
#1511
01
#1512
11
#1513
01
03
#1514
b110 /
11
#1515
01
#1516
b100 /
10
11
#1517
01
#1518
b0011 .
b000 /
00
11
#1519
01
#1520
11
#1521
01
13
#1522
b001 /
11
#1523
01
#1524
b011 /
11
#1525
01
#1526
b111 /
11
#1527
01
#1528
11
#1529
01
03
#1530
b110 /
11
#1531
01
#1532
b100 /
10
11
#1533
01
#1534
b0001000011 #
b0100 .
b000 /
00
11
#1535
01
#1536
11
#1537
01
13
#1538
b001 /
11
#1539
01
#1540
b011 /
11
#1541
01
#1542
b111 /
11
#1543
01
#1544
11
#1545
01
03
