DigitalCircuitsExperiments/DCE03/ALU32/ALU32_Test/ALU32_TestAll/ALU32_TestAll.v
module ALU32_TestAll (sub_add, a, b, carry, zero, overflow, result);
    input sub_add;// This is a switch of Add(0) or Sub(1)
    input [31:0] a; // This is a Complement number
    input [31:0] b; // This is a Complement number
    output reg [0:0] carry;
    output reg zero, overflow;
    output reg [31:0] result;
    reg [31:0] b_withCin;

    always @(*) 
    /* verilator lint_off WIDTH */
    begin
        assign b_withCin = ({32{sub_add}}^b) + sub_add;
        assign result = a + b_withCin;
        assign carry = a[30] == 1 && b[30] == 1;
        assign overflow = (a[31] == b_withCin[31] && result[31] != a[31]);
        assign zero = ~(| result);
    end
    /* verilator lint_on WIDTH */

    /* verilator lint_off IMPLICIT */

    // Give result of test bench F1S1B1T1
    reg [31:0] testF1S1B1T1_expected_result;
    reg [0:0] testF1S1B1T1_expected_carry;
    reg testF1S1B1T1_expected_zero, testF1S1B1T1_expected_overflow;
    assign testF1S1B1T1_expected_result = 32'b00110011100000101001101110011100;
    assign testF1S1B1T1_expected_carry = 1'b0;
    assign testF1S1B1T1_expected_overflow = 0;
    assign testF1S1B1T1_expected_zero = 0;

    // Give result of test bench F1S1B1T2
    reg [31:0] testF1S1B1T2_expected_result;
    reg [0:0] testF1S1B1T2_expected_carry;
    reg testF1S1B1T2_expected_zero, testF1S1B1T2_expected_overflow;
    assign testF1S1B1T2_expected_result = 32'b00000000000000000000000000000000;
    assign testF1S1B1T2_expected_carry = 1'b0;
    assign testF1S1B1T2_expected_overflow = 0;
    assign testF1S1B1T2_expected_zero = 0;

    // Give result of test bench F1S1B1T3
    reg [31:0] testF1S1B1T3_expected_result;
    reg [0:0] testF1S1B1T3_expected_carry;
    reg testF1S1B1T3_expected_zero, testF1S1B1T3_expected_overflow;
    assign testF1S1B1T3_expected_result = 32'b11110001010010000110010111011111;
    assign testF1S1B1T3_expected_carry = 1'b0;
    assign testF1S1B1T3_expected_overflow = 0;
    assign testF1S1B1T3_expected_zero = 0;

    // Give result of test bench F1S1B2T1
    reg [31:0] testF1S1B2T1_expected_result;
    reg [0:0] testF1S1B2T1_expected_carry;
    reg testF1S1B2T1_expected_zero, testF1S1B2T1_expected_overflow;
    assign testF1S1B2T1_expected_result = 32'b01000010001110100011010111000110;
    assign testF1S1B2T1_expected_carry = 1'b0;
    assign testF1S1B2T1_expected_overflow = 0;
    assign testF1S1B2T1_expected_zero = 0;

    // Give result of test bench F1S1B2T2
    reg [31:0] testF1S1B2T2_expected_result;
    reg [0:0] testF1S1B2T2_expected_carry;
    reg testF1S1B2T2_expected_zero, testF1S1B2T2_expected_overflow;
    assign testF1S1B2T2_expected_result = 32'b00000000000000000000000000000000;
    assign testF1S1B2T2_expected_carry = 1'b0;
    assign testF1S1B2T2_expected_overflow = 0;
    assign testF1S1B2T2_expected_zero = 0;

    // Give result of test bench F1S1B3T1
    reg [31:0] testF1S1B3T1_expected_result;
    reg [0:0] testF1S1B3T1_expected_carry;
    reg testF1S1B3T1_expected_zero, testF1S1B3T1_expected_overflow;
    assign testF1S1B3T1_expected_result = 32'b10111101110001011100101000111010;
    assign testF1S1B3T1_expected_carry = 1'b0;
    assign testF1S1B3T1_expected_overflow = 0;
    assign testF1S1B3T1_expected_zero = 0;

    // Give result of test bench F1S1B3T2
    reg [31:0] testF1S1B3T2_expected_result;
    reg [0:0] testF1S1B3T2_expected_carry;
    reg testF1S1B3T2_expected_zero, testF1S1B3T2_expected_overflow;
    assign testF1S1B3T2_expected_result = 32'b00000000000000000000000000000000;
    assign testF1S1B3T2_expected_carry = 1'b0;
    assign testF1S1B3T2_expected_overflow = 0;
    assign testF1S1B3T2_expected_zero = 0;

    // Give result of test bench F1S2B1T1
    reg [31:0] testF1S2B1T1_expected_result;
    reg [0:0] testF1S2B1T1_expected_carry;
    reg testF1S2B1T1_expected_zero, testF1S2B1T1_expected_overflow;
    assign testF1S2B1T1_expected_result = 32'b01000110101011101010000101010100;
    assign testF1S2B1T1_expected_carry = 1'b0;
    assign testF1S2B1T1_expected_overflow = 0;
    assign testF1S2B1T1_expected_zero = 0;

    // Give result of test bench F2S1B1T1
    reg [31:0] testF2S1B1T1_expected_result;
    reg [0:0] testF2S1B1T1_expected_carry;
    reg testF2S1B1T1_expected_zero, testF2S1B1T1_expected_overflow;
    assign testF2S1B1T1_expected_result = 32'b01000010001110100011010111000110;
    assign testF2S1B1T1_expected_carry = 1'b0;
    assign testF2S1B1T1_expected_overflow = 0;
    assign testF2S1B1T1_expected_zero = 0;

    // Give result of test bench F2S1B2T1
    reg [31:0] testF2S1B2T1_expected_result;
    reg [0:0] testF2S1B2T1_expected_carry;
    reg testF2S1B2T1_expected_zero, testF2S1B2T1_expected_overflow;
    assign testF2S1B2T1_expected_result = 32'b00110011100000101001101110011100;
    assign testF2S1B2T1_expected_carry = 1'b0;
    assign testF2S1B2T1_expected_overflow = 0;
    assign testF2S1B2T1_expected_zero = 0;

    // Give result of test bench F2S1B2T2
    reg [31:0] testF2S1B2T2_expected_result;
    reg [0:0] testF2S1B2T2_expected_carry;
    reg testF2S1B1T2_expected_zero, testF2S1B1T2_expected_overflow;
    assign testF2S1B2T2_expected_result = 32'b00000000000000000000000000000000;
    assign testF2S1B2T2_expected_carry = 1'b0;
    assign testF2S1B2T2_expected_overflow = 0;
    assign testF2S1B2T2_expected_zero = 0;

    // Give result of test bench F2S1B2T3
    reg [31:0] testF2S1B2T3_expected_result;
    reg [0:0] testF2S1B2T3_expected_carry;
    reg testF2S1B1T3_expected_zero, testF2S1B1T3_expected_overflow;
    assign testF2S1B2T3_expected_result = 32'b11001100011111010110010001100100;
    assign testF2S1B2T3_expected_carry = 1'b0;
    assign testF2S1B2T3_expected_overflow = 0;
    assign testF2S1B2T3_expected_zero = 0;

    // Give result of test bench F2S1B3T1
    reg [31:0] testF2S1B3T1_expected_result;
    reg [0:0] testF2S1B3T1_expected_carry;
    reg testF2S1B3T1_expected_zero, testF2S1B3T1_expected_overflow;
    assign testF2S1B3T1_expected_result = 32'b11001100011111010110010001100100;
    assign testF2S1B3T1_expected_carry = 1'b0;
    assign testF2S1B3T1_expected_overflow = 0;
    assign testF2S1B3T1_expected_zero = 0;

    // Give result of test bench F2S1B3T2
    reg [31:0] testF2S1B3T2_expected_result;
    reg [0:0] testF2S1B3T2_expected_carry;
    reg testF2S1B3T2_expected_zero, testF2S1B3T2_expected_overflow;
    assign testF2S1B3T2_expected_result = 32'b00000000000000000000000000000000;
    assign testF2S1B3T2_expected_carry = 1'b0;
    assign testF2S1B3T2_expected_overflow = 0;
    assign testF2S1B3T2_expected_zero = 0;

    // Give result of test bench F2S1B3T3
    reg [31:0] testF2S1B3T3_expected_result;
    reg [0:0] testF2S1B3T3_expected_carry;
    reg testF2S1B3T3_expected_zero, testF2S1B3T3_expected_overflow;
    assign testF2S1B3T3_expected_result = 32'b00110011100000101001101110011100;
    assign testF2S1B3T3_expected_carry = 1'b0;
    assign testF2S1B3T3_expected_overflow = 0;
    assign testF2S1B3T3_expected_zero = 0;

    /* verilator lint_on IMPLICIT */

endmodule

DigitalCircuitsExperiments/DCE03/ALU32/ALU32_Test/ALU32_TestAll/obj_dir/dump.vcd
$version Generated by VerilatedVcd $end
$timescale 1s $end

 $scope module TOP $end
  $var wire 32 $ a [31:0] $end
  $var wire 32 % b [31:0] $end
  $var wire  1 & carry [0:0] $end
  $var wire  1 ( overflow $end
  $var wire 32 ) result [31:0] $end
  $var wire  1 # sub_add $end
  $var wire  1 ' zero $end
  $scope module ALU32_TestAll $end
   $var wire 32 $ a [31:0] $end
   $var wire 32 % b [31:0] $end
   $var wire 32 * b_withCin [31:0] $end
   $var wire  1 & carry [0:0] $end
   $var wire  1 ( overflow $end
   $var wire 32 ) result [31:0] $end
   $var wire  1 # sub_add $end
   $var wire  1 , testF1S1B1T1_expected_carry [0:0] $end
   $var wire  1 , testF1S1B1T1_expected_overflow $end
   $var wire 32 + testF1S1B1T1_expected_result [31:0] $end
   $var wire  1 , testF1S1B1T1_expected_zero $end
   $var wire  1 , testF1S1B1T2_expected_carry [0:0] $end
   $var wire  1 , testF1S1B1T2_expected_overflow $end
   $var wire 32 - testF1S1B1T2_expected_result [31:0] $end
   $var wire  1 , testF1S1B1T2_expected_zero $end
   $var wire  1 , testF1S1B1T3_expected_carry [0:0] $end
   $var wire  1 , testF1S1B1T3_expected_overflow $end
   $var wire 32 . testF1S1B1T3_expected_result [31:0] $end
   $var wire  1 , testF1S1B1T3_expected_zero $end
   $var wire  1 , testF1S1B2T1_expected_carry [0:0] $end
   $var wire  1 , testF1S1B2T1_expected_overflow $end
   $var wire 32 / testF1S1B2T1_expected_result [31:0] $end
   $var wire  1 , testF1S1B2T1_expected_zero $end
   $var wire  1 , testF1S1B2T2_expected_carry [0:0] $end
   $var wire  1 , testF1S1B2T2_expected_overflow $end
   $var wire 32 - testF1S1B2T2_expected_result [31:0] $end
   $var wire  1 , testF1S1B2T2_expected_zero $end
   $var wire  1 , testF1S1B3T1_expected_carry [0:0] $end
   $var wire  1 , testF1S1B3T1_expected_overflow $end
   $var wire 32 0 testF1S1B3T1_expected_result [31:0] $end
   $var wire  1 , testF1S1B3T1_expected_zero $end
   $var wire  1 , testF1S1B3T2_expected_carry [0:0] $end
   $var wire  1 , testF1S1B3T2_expected_overflow $end
   $var wire 32 - testF1S1B3T2_expected_result [31:0] $end
   $var wire  1 , testF1S1B3T2_expected_zero $end
   $var wire  1 , testF1S2B1T1_expected_carry [0:0] $end
   $var wire  1 , testF1S2B1T1_expected_overflow $end
   $var wire 32 1 testF1S2B1T1_expected_result [31:0] $end
   $var wire  1 , testF1S2B1T1_expected_zero $end
   $var wire  1 , testF2S1B1T1_expected_carry [0:0] $end
   $var wire  1 , testF2S1B1T1_expected_overflow $end
   $var wire 32 / testF2S1B1T1_expected_result [31:0] $end
   $var wire  1 , testF2S1B1T1_expected_zero $end
   $var wire  1 , testF2S1B2T1_expected_carry [0:0] $end
   $var wire  1 , testF2S1B2T1_expected_overflow $end
   $var wire 32 + testF2S1B2T1_expected_result [31:0] $end
   $var wire  1 , testF2S1B2T1_expected_zero $end
   $var wire  1 , testF2S1B2T2_expected_carry [0:0] $end
   $var wire  1 , testF2S1B2T2_expected_overflow $end
   $var wire 32 - testF2S1B2T2_expected_result [31:0] $end
   $var wire  1 , testF2S1B2T2_expected_zero $end
   $var wire  1 , testF2S1B2T3_expected_carry [0:0] $end
   $var wire  1 , testF2S1B2T3_expected_overflow $end
   $var wire 32 2 testF2S1B2T3_expected_result [31:0] $end
   $var wire  1 , testF2S1B2T3_expected_zero $end
   $var wire  1 , testF2S1B3T1_expected_carry [0:0] $end
   $var wire  1 , testF2S1B3T1_expected_overflow $end
   $var wire 32 2 testF2S1B3T1_expected_result [31:0] $end
   $var wire  1 , testF2S1B3T1_expected_zero $end
   $var wire  1 , testF2S1B3T2_expected_carry [0:0] $end
   $var wire  1 , testF2S1B3T2_expected_overflow $end
   $var wire 32 - testF2S1B3T2_expected_result [31:0] $end
   $var wire  1 , testF2S1B3T2_expected_zero $end
   $var wire  1 , testF2S1B3T3_expected_carry [0:0] $end
   $var wire  1 , testF2S1B3T3_expected_overflow $end
   $var wire 32 + testF2S1B3T3_expected_result [31:0] $end
   $var wire  1 , testF2S1B3T3_expected_zero $end
   $var wire  1 ' zero $end
  $upscope $end
 $upscope $end
$enddefinitions $end


#1
0#
b00111010110111100110100010110001 $
b11111000101001000011001011101011 %
0&
0'
0(
b00110011100000101001101110011100 )
b11111000101001000011001011101011 *
b00110011100000101001101110011100 +
0,
b00000000000000000000000000000000 -
b11110001010010000110010111011111 .
b01000010001110100011010111000110 /
b10111101110001011100101000111010 0
b01000110101011101010000101010100 1
b11001100011111010110010001100100 2
#2
b11000101001000011001011101001111 %
1'
b00000000000000000000000000000000 )
b11000101001000011001011101001111 *
#3
b10110110011010011111110100101110 %
0'
b11110001010010000110010111011111 )
b10110110011010011111110100101110 *
#4
b00000111010110111100110100010101 %
b01000010001110100011010111000110 )
b00000111010110111100110100010101 *
#5
b00000000000000000000000000000000 $
b00000000000000000000000000000000 %
1'
b00000000000000000000000000000000 )
b00000000000000000000000000000000 *
#6
b11000101001000011001011101001111 $
b11111000101001000011001011101011 %
1&
0'
b10111101110001011100101000111010 )
b11111000101001000011001011101011 *
#7
b00000000000000000000000000000000 $
b00000000000000000000000000000000 %
0&
1'
b00000000000000000000000000000000 )
b00000000000000000000000000000000 *
#8
b01100011010101110101000010101010 $
b01100011010101110101000010101010 %
1&
0'
1(
b11000110101011101010000101010100 )
b01100011010101110101000010101010 *
#9
1#
b00111010110111100110100010110001 $
b11111000101001000011001011101011 %
0&
0(
b01000010001110100011010111000110 )
b00000111010110111100110100010101 *
#10
b00000111010110111100110100010101 %
b00110011100000101001101110011100 )
b11111000101001000011001011101011 *
#11
b00000000000000000000000000000000 $
b00000000000000000000000000000000 %
1'
b00000000000000000000000000000000 )
b00000000000000000000000000000000 *
#12
b00000111010110111100110100010101 $
b00111010110111100110100010110001 %
0'
b11001100011111010110010001100100 )
b11000101001000011001011101001111 *
#13
b11000101001000011001011101001111 $
b11111000101001000011001011101011 %
1&
b00000111010110111100110100010101 *
#14
b00000000000000000000000000000000 $
b00000000000000000000000000000000 %
0&
1'
b00000000000000000000000000000000 )
b00000000000000000000000000000000 *
#15
b11111000101001000011001011101011 $
b11000101001000011001011101001111 %
1&
0'
b00110011100000101001101110011100 )
b00111010110111100110100010110001 *
