DigitalCircuitsExperiments/DCE03/add_datastream_4/add_datastream_4.v
module add_datastream_1(in_x, in_y, out_s);
    input [3:0] in_x, in_y;
    output [3:0] out_s;

    assign out_s = in_x + in_y;
endmodule

DigitalCircuitsExperiments/DCE03/add_datastream_4/obj_dir/dump.vcd
$version Generated by VerilatedVcd $end
$timescale 1s $end

 $scope module TOP $end
  $var wire  4 # in_x [3:0] $end
  $var wire  4 $ in_y [3:0] $end
  $var wire  4 % out_s [3:0] $end
  $scope module add_datastream_1 $end
   $var wire  4 # in_x [3:0] $end
   $var wire  4 $ in_y [3:0] $end
   $var wire  4 % out_s [3:0] $end
  $upscope $end
 $upscope $end
$enddefinitions $end


#1
b0000 #
b0000 $
b0000 %
#2
b0001 $
b0001 %
#3
b0010 $
b0010 %
#4
b0011 $
b0011 %
#5
b0100 $
b0100 %
#6
b0101 $
b0101 %
#7
b0110 $
b0110 %
#8
b0111 $
b0111 %
#9
b1000 $
b1000 %
#10
b1001 $
b1001 %
#11
b1010 $
b1010 %
#12
b1011 $
b1011 %
#13
b1100 $
b1100 %
#14
b1101 $
b1101 %
#15
b1110 $
b1110 %
#16
b1111 $
b1111 %
#17
b0001 #
b0000 $
b0001 %
#18
b0001 $
b0010 %
#19
b0010 $
b0011 %
#20
b0011 $
b0100 %
#21
b0100 $
b0101 %
#22
b0101 $
b0110 %
#23
b0110 $
b0111 %
#24
b0111 $
b1000 %
#25
b1000 $
b1001 %
#26
b1001 $
b1010 %
#27
b1010 $
b1011 %
#28
b1011 $
b1100 %
#29
b1100 $
b1101 %
#30
b1101 $
b1110 %
#31
b1110 $
b1111 %
#32
b1111 $
b0000 %
#33
b0010 #
b0000 $
b0010 %
#34
b0001 $
b0011 %
#35
b0010 $
b0100 %
#36
b0011 $
b0101 %
#37
b0100 $
b0110 %
#38
b0101 $
b0111 %
#39
b0110 $
b1000 %
#40
b0111 $
b1001 %
#41
b1000 $
b1010 %
#42
b1001 $
b1011 %
#43
b1010 $
b1100 %
#44
b1011 $
b1101 %
#45
b1100 $
b1110 %
#46
b1101 $
b1111 %
#47
b1110 $
b0000 %
#48
b1111 $
b0001 %
#49
b0011 #
b0000 $
b0011 %
#50
b0001 $
b0100 %
#51
b0010 $
b0101 %
#52
b0011 $
b0110 %
#53
b0100 $
b0111 %
#54
b0101 $
b1000 %
#55
b0110 $
b1001 %
#56
b0111 $
b1010 %
#57
b1000 $
b1011 %
#58
b1001 $
b1100 %
#59
b1010 $
b1101 %
#60
b1011 $
b1110 %
#61
b1100 $
b1111 %
#62
b1101 $
b0000 %
#63
b1110 $
b0001 %
#64
b1111 $
b0010 %
#65
b0100 #
b0000 $
b0100 %
#66
b0001 $
b0101 %
#67
b0010 $
b0110 %
#68
b0011 $
b0111 %
#69
b0100 $
b1000 %
#70
b0101 $
b1001 %
#71
b0110 $
b1010 %
#72
b0111 $
b1011 %
#73
b1000 $
b1100 %
#74
b1001 $
b1101 %
#75
b1010 $
b1110 %
#76
b1011 $
b1111 %
#77
b1100 $
b0000 %
#78
b1101 $
b0001 %
#79
b1110 $
b0010 %
#80
b1111 $
b0011 %
#81
b0101 #
b0000 $
b0101 %
#82
b0001 $
b0110 %
#83
b0010 $
b0111 %
#84
b0011 $
b1000 %
#85
b0100 $
b1001 %
#86
b0101 $
b1010 %
#87
b0110 $
b1011 %
#88
b0111 $
b1100 %
#89
b1000 $
b1101 %
#90
b1001 $
b1110 %
#91
b1010 $
b1111 %
#92
b1011 $
b0000 %
#93
b1100 $
b0001 %
#94
b1101 $
b0010 %
#95
b1110 $
b0011 %
#96
b1111 $
b0100 %
#97
b0110 #
b0000 $
b0110 %
#98
b0001 $
b0111 %
#99
b0010 $
b1000 %
#100
b0011 $
b1001 %
#101
b0100 $
b1010 %
#102
b0101 $
b1011 %
#103
b0110 $
b1100 %
#104
b0111 $
b1101 %
#105
b1000 $
b1110 %
#106
b1001 $
b1111 %
#107
b1010 $
b0000 %
#108
b1011 $
b0001 %
#109
b1100 $
b0010 %
#110
b1101 $
b0011 %
#111
b1110 $
b0100 %
#112
b1111 $
b0101 %
#113
b0111 #
b0000 $
b0111 %
#114
b0001 $
b1000 %
#115
b0010 $
b1001 %
#116
b0011 $
b1010 %
#117
b0100 $
b1011 %
#118
b0101 $
b1100 %
#119
b0110 $
b1101 %
#120
b0111 $
b1110 %
#121
b1000 $
b1111 %
#122
b1001 $
b0000 %
#123
b1010 $
b0001 %
#124
b1011 $
b0010 %
#125
b1100 $
b0011 %
#126
b1101 $
b0100 %
#127
b1110 $
b0101 %
#128
b1111 $
b0110 %
#129
b1000 #
b0000 $
b1000 %
#130
b0001 $
b1001 %
#131
b0010 $
b1010 %
#132
b0011 $
b1011 %
#133
b0100 $
b1100 %
#134
b0101 $
b1101 %
#135
b0110 $
b1110 %
#136
b0111 $
b1111 %
#137
b1000 $
b0000 %
#138
b1001 $
b0001 %
#139
b1010 $
b0010 %
#140
b1011 $
b0011 %
#141
b1100 $
b0100 %
#142
b1101 $
b0101 %
#143
b1110 $
b0110 %
#144
b1111 $
b0111 %
#145
b1001 #
b0000 $
b1001 %
#146
b0001 $
b1010 %
#147
b0010 $
b1011 %
#148
b0011 $
b1100 %
#149
b0100 $
b1101 %
#150
b0101 $
b1110 %
#151
b0110 $
b1111 %
#152
b0111 $
b0000 %
#153
b1000 $
b0001 %
#154
b1001 $
b0010 %
#155
b1010 $
b0011 %
#156
b1011 $
b0100 %
#157
b1100 $
b0101 %
#158
b1101 $
b0110 %
#159
b1110 $
b0111 %
#160
b1111 $
b1000 %
#161
b1010 #
b0000 $
b1010 %
#162
b0001 $
b1011 %
#163
b0010 $
b1100 %
#164
b0011 $
b1101 %
#165
b0100 $
b1110 %
#166
b0101 $
b1111 %
#167
b0110 $
b0000 %
#168
b0111 $
b0001 %
#169
b1000 $
b0010 %
#170
b1001 $
b0011 %
#171
b1010 $
b0100 %
#172
b1011 $
b0101 %
#173
b1100 $
b0110 %
#174
b1101 $
b0111 %
#175
b1110 $
b1000 %
#176
b1111 $
b1001 %
#177
b1011 #
b0000 $
b1011 %
#178
b0001 $
b1100 %
#179
b0010 $
b1101 %
#180
b0011 $
b1110 %
#181
b0100 $
b1111 %
#182
b0101 $
b0000 %
#183
b0110 $
b0001 %
#184
b0111 $
b0010 %
#185
b1000 $
b0011 %
#186
b1001 $
b0100 %
#187
b1010 $
b0101 %
#188
b1011 $
b0110 %
#189
b1100 $
b0111 %
#190
b1101 $
b1000 %
#191
b1110 $
b1001 %
#192
b1111 $
b1010 %
#193
b1100 #
b0000 $
b1100 %
#194
b0001 $
b1101 %
#195
b0010 $
b1110 %
#196
b0011 $
b1111 %
#197
b0100 $
b0000 %
#198
b0101 $
b0001 %
#199
b0110 $
b0010 %
#200
b0111 $
b0011 %
#201
b1000 $
b0100 %
#202
b1001 $
b0101 %
#203
b1010 $
b0110 %
#204
b1011 $
b0111 %
#205
b1100 $
b1000 %
#206
b1101 $
b1001 %
#207
b1110 $
b1010 %
#208
b1111 $
b1011 %
#209
b1101 #
b0000 $
b1101 %
#210
b0001 $
b1110 %
#211
b0010 $
b1111 %
#212
b0011 $
b0000 %
#213
b0100 $
b0001 %
#214
b0101 $
b0010 %
#215
b0110 $
b0011 %
#216
b0111 $
b0100 %
#217
b1000 $
b0101 %
#218
b1001 $
b0110 %
#219
b1010 $
b0111 %
#220
b1011 $
b1000 %
#221
b1100 $
b1001 %
#222
b1101 $
b1010 %
#223
b1110 $
b1011 %
#224
b1111 $
b1100 %
#225
b1110 #
b0000 $
b1110 %
#226
b0001 $
b1111 %
#227
b0010 $
b0000 %
#228
b0011 $
b0001 %
#229
b0100 $
b0010 %
#230
b0101 $
b0011 %
#231
b0110 $
b0100 %
#232
b0111 $
b0101 %
#233
b1000 $
b0110 %
#234
b1001 $
b0111 %
#235
b1010 $
b1000 %
#236
b1011 $
b1001 %
#237
b1100 $
b1010 %
#238
b1101 $
b1011 %
#239
b1110 $
b1100 %
#240
b1111 $
b1101 %
#241
b1111 #
b0000 $
b1111 %
#242
b0001 $
b0000 %
#243
b0010 $
b0001 %
#244
b0011 $
b0010 %
#245
b0100 $
b0011 %
#246
b0101 $
b0100 %
#247
b0110 $
b0101 %
#248
b0111 $
b0110 %
#249
b1000 $
b0111 %
#250
b1001 $
b1000 %
#251
b1010 $
b1001 %
#252
b1011 $
b1010 %
#253
b1100 $
b1011 %
#254
b1101 $
b1100 %
#255
b1110 $
b1101 %
#256
b1111 $
b1110 %
